Workbook

Sheet General Information
B2: PSAP Security Practices — Assessment Matrix
B4: This workbook is a companion to the PSAP Security Practices Posture Assessment report. It documents implementation status at the individual assessment item level and provides quantitative scoring to support baseline tracking, trend analysis, and comparison across future assessment cycles.
B8: Workbook Structure
B9: Question Set — | D9: Contains the 198 assessment items organized by domain and category, along with the assessment question text, PSAP-provided comments and supporting information, the assessed rating for each item, and discrepancy comments where the assessed rating differs from the PSAP's initial self-reported rating.
D12: Ratings use the following scale: - Yes (3) - In Progress (2) - Planned (1) - No (0) - Unknown (0) - Not Applicable (excluded from scoring)
B20: Full Score Table — | D20: Displays rating distribution counts by category and domain, with weighted point totals and maximum possible scores. Items rated 'Not Applicable' are excluded from point calculations.
B23: Domain-Level Score Table — | D23: Summarizes rating distribution, point totals, and maximum possible scores at the domain level.
B25: Bar Chart — | D25: Visualizes domain-level implementation scores as a percentage of maximum possible points, with a target threshold for reference.
B28: Radar Chart — | D28: Visualizes domain-level implementation percentages in a radar (spider) format to illustrate relative strength and coverage across all 13 assessment domains.
B33: Assessment Framework
B35: This assessment is anchored in two complementary references: the NENA Security for Next Generation 9-1-1 Standard (NG-SEC) [NENA-STA-040.2-2024], which defines security outcomes and requirements for NG9-1-1 environments, and NIST Special Publication 800-53 Revision 5, which provides a detailed catalog of security and privacy controls. The 198 assessment items in this workbook are organized across 13 security domains and 51 categories derived from these frameworks.
B40: Scoring
B42: Each assessment item is rated on a 0-3 implementation scale. Point totals are calculated by weighting each rating ('Unknown' = 0, 'No' = 0, 'Planned' = 1, 'In Progress' = 2, 'Yes' = 3) and summing across applicable items. Items rated 'Not Applicable' are excluded from both the point total and the maximum possible score, so that percentages reflect only items within the scope for the assessed environment. The maximum possible score for any category or domain represents full implementation (a rating of 'Yes') for all applicable items.
B47: Target Implementation Threshold
B49: The target implementation threshold defines the minimum acceptable implementation percentage used as a reference point ('Goal') in the Bar Chart and Radar Chart visualizations. This threshold can be configured below and applies uniformly across all domains.
B51: — Target Threshold Value — | E51: 0.5

Sheet PSAP Information
A1: PSAP | C1: Sample County 911 Communications
A2: Address | C2: 100 Public Safety Drive
A3: City/ZIP | C3: Anytown | 00000
A5: PSAP Director | C5: Jane Smith
A6: Director Phone # | C6: 555-000-0000
A7: Director Email | C7: jsmith@samplecounty.gov
A9: Registration Date | C9: 45672
A10: Final Domain Survey Complete | C10: 45689
A11: Site Visit Date
A13: Target Maturity Score | B13: ='General Information'!$E$51 -> 0.5
A15: Domain Survey Information: | C15: Stakeholders providing input: | D15: Date Completed:
A16: Domain 1 | C16: IT Director Director of 911 Operations | D16: 45689
A17: Domain 2 | C17: IT Director Director of 911 Operations | D17: 45689
A18: Domain 3 | C18: IT Director Director of 911 Operations | D18: 45689
A19: Domain 4 | C19: IT Director Director of 911 Operations | D19: 45689
A20: Domain 5 | C20: IT Director Director of 911 Operations | D20: 45689
A21: Domain 6 | C21: IT Director Director of 911 Operations | D21: 45689
A22: Domain 7 | C22: IT Director Director of 911 Operations | D22: 45689
A23: Domain 8 | C23: IT Director Director of 911 Operations | D23: 45689
A24: Domain 9 | C24: IT Director Director of 911 Operations | D24: 45689
A25: Domain 10 | C25: IT Director Director of 911 Operations | D25: 45689
A26: Domain 11 | C26: IT Director Director of 911 Operations | D26: 45689
A27: Domain 12 | C27: IT Director Director of 911 Operations | D27: 45689
A28: Domain 13 | C28: IT Director Director of 911 Operations | D28: 45689

Sheet Question Set
A1: ID | E1: Question Text, Follow Up Question & Implementation Example | F1: Comments & Additional Information | G1: Assessed Rating
B2: 1. Governance, Risk & Strategy
C3: A. Executive Leadership & Resource Allocation
A4: 1A-1 | D4: 1. | E4: Do executive leaders – such as the CEO, City Manager, or Board members – formally review and approve cybersecurity and privacy policies and strategic security plans to ensure legal compliance and alignment with public safety goals? If yes, please list the executives involved and how often these documents are reviewed or updated. (Example: “Our City Manager and Legal Counsel review the policy annually in Q1.”) | F4: Scheduled for a future implementation cycle. | G4: PLANNED
A5: 1A-2 | D5: 2. | E5: Does senior management designate a cybersecurity and privacy lead for your Emergency Communications Center (ECC) or Public Safety Answering Point (PSAP) and allocate appropriate staff resources, tools, and budget to safeguard these mission-critical services? If yes, please name the role or individual and briefly describe the staffing, technology, or budget they’ve been allocated. (Example: “Our Chief Technology Officer is the official ECC/PSAP Security Lead, supported by a three-person team and a dedicated $50K annual budget.”) | F5: Implemented and documented. | G5: YES
A6: 1A-3 | D6: 3. | E6: Do senior leaders regularly monitor emerging threats – such as ransomware or service outages – that could disrupt 9-1-1 or emergency response operations? If yes, please describe how they stay informed and how often they review threat reports. (Example: “They receive a weekly threat summary from our SOC (Security Operations Center) and meet monthly to discuss high-risk alerts.”) | F6: Controls are in place and verified. | G6: YES
C8: B. Policy & Asset Inventory Management
A9: 1B-1 | D9: 1. | E9: Do your emergency communications cybersecurity and privacy policies: * Explicitly reference all applicable laws and regulations (e.g., CJIS, state privacy laws) * Include security controls aligned with the risks identified for your mission- critical systems If yes, please explain which laws you follow and name one or two key controls you’ve implemented. (Example: “We comply with CJIS requirements. We enforce multifactor authentication and daily log reviews for all dispatch consoles.”) | F9: Process is established and followed. | G9: YES
A10: 1B-2 | D10: 2. | E10: Has senior leadership formally approved – and do they oversee – a policy that outlines how you: * Maintain an up-to-date inventory of every 9-1-1 and related system (e.g., call- handling platforms, mapping tools, logging servers) * Regularly review that inventory to support informed decisions and protect sensitive data If yes, please briefly describe where this policy is documented and how reviews are scheduled. (Example: “Our City IT Director signs off on the policy each January. The Operations team updates the inventory quarterly.”) | F10: Not yet implemented. | G10: NO
A11: 1B-3 | D11: 3. | E11: Do you have formal, written plans for systems like CAD (Computer-Aided Dispatch), CPE/CHE (Call Processing/Call Handling Equipment), GIS (Mapping), and others that: * Assign clear roles and responsibilities for each system * Explain how systems are categorized by importance and data sensitivity * Describe how devices connect and exchange information * Are updated following regular risk reviews If yes, please list the systems covered and where the most current version of each plan is stored. (Example: “Our CAD and GIS plans are stored in SharePoint. We update them after our annual risk assessment each October.”) | F11: Identified as a gap; not yet addressed. | G11: NO
C13: C. Role Definition & Governance Oversight
A14: 1C-1 | D14: 1. | E14: Has your organization empowered a senior executive and a formal governance group (e.g., a steering committee or board) to: * Set cybersecurity and privacy priorities * Review performance metrics and reports * Ensure alignment with public safety goals and legal and regulatory requirements If yes, please name the executive role and the governance body, and describe how often they meet. (Example: “The Assistant City Manager chairs our Cyber Risk Committee, which meets quarterly.”) | F14: Practice is mature and consistent. | G14: YES
A15: 1C-2 | D15: 2. | E15: Do the people who “own” your data (e.g., operations managers) and those who “manage” it (e.g., IT staff) participate in a formal data governance process that: * Defines how you classify data by sensitivity (public, internal, confidential) * Sets rules for sharing data internally or with partners * Regularly reviews and updates those policies If yes, please list the roles involved and how frequently your data governance group meets or reviews policies. (Example: “Our Data Governance Board includes the CAD Manager and the CIO. They review classification rules annually.”) | F15: Process does not currently exist. | G15: NO
A16: 1C-3 | D16: 3. | E16: Does your organization employ enough trained personnel, either internally or with contractors, with clear job descriptions, to: * Set up systems securely * Monitor security in real time * Respond to incidents * Perform audit reviews If yes, please describe your security team structure (titles or roles) and approximate staffing levels. (Example: “We have a two-person SOC (Security Operations Center) team, plus one external consultant on retainer.”) | F16: Fully implemented per current policy. | G16: YES
A17: 1C-4 | D17: 4. | E17: Do you have documented roles and processes, including acceptable use rules and background checks where required, for granting, changing, and removing access to: * Critical systems (e.g., dispatch consoles, admin portals) * Secure facilities (e.g., data centers, control rooms) If yes, please outline who approves access and what screening or rules apply. (Example: “Managers approve console access; all new hires undergo a criminal background check.”) | F17: In place; reviewed periodically. | G17: YES
A18: 1C-5 | D18: 5. | E18: Do you have written procedures that cover: * Secure system configuration * System log monitoring * Incident detection and reporting * Risk assessments * Remediation tracking across all 9-1-1 platforms (e.g., call handling, mapping, back-end servers) If yes, please indicate where these documents are stored (e.g., SharePoint folder) and how they’re kept up to date. (Example: “All procedures are in our Policy Manual, updated after each quarterly risk review.”) | F18: Working to formalize this process. | G18: IN PROGRESS
C20: D. Risk Assessment & Management Strategy
A21: 1D-1 | D21: 1. | E21: Do you maintain a written risk management strategy that: * Reflects your organization’s risk appetite (how much risk you’re willing to accept) * Addresses multiple threat vectors (e.g., phishing, malware, supplier issues, and denial-of-service attacks) * Is reviewed and updated on a regular schedule If yes, please note where the strategy is documented and when the last review occurred. (Example: “Our Risk Strategy lives in the Policy Manual; last reviewed January 2025.”) | F21: Documentation is in development. | G21: IN PROGRESS
A22: 1D-2 | D22: 2. | E22: Have you categorized all systems and data sets by their sensitivity and operational criticality – specifically considering Confidentiality, Integrity, and Availability – and used this framework to define risk levels and select appropriate security controls? If yes, please share your categorization scheme (for example, “High, Medium, Low”) and one or two controls you apply at each level. (Example: “‘High Impact’ systems require daily backups and multifactor authentication.”) | F22: No formal controls in place. | G22: NO
A23: 1D-3 | D23: 3. | E23: Does your organization have written policies and procedures that spell out: * Scope – which public safety systems (e.g., CAD, call routing, GIS, etc.) must be assessed * Frequency – how often you run those assessments * Roles – who leads and who supports each assessment * Methods – what tools or techniques are used (e.g., interviews, automated scans, tabletop exercises) If yes, please indicate where these documents are stored and when they were last updated. (Example: “Our Risk Assessment SOP is in SharePoint; it was updated in September 2024.”) | F23: Not currently in scope; noted as a gap. | G23: NO
A24: 1D-4 | D24: 4. | E24: Do you conduct formal risk assessments that: * Identify likely ways an attacker or failure could impact you (e.g., technical flaws, vendor issues, user errors) * Evaluate each risk based on its potential impact on service (slowed or lost dispatch), data (confidentiality breach), or life safety (9-1-1 delays) If yes, please describe which threat categories you cover and how you score their impacts. (Example: “We rate each scenario on a 1–5 scale for service outage and data loss.”) | F24: This has not been established. | G24: NO
A25: 1D-5 | D25: 5. | E25: Do you use the outcomes of your risk assessments to: * Prioritize which systems to monitor more closely * Decide what mitigation steps to take first * Regularly review the assessment process and the overall risk strategy to keep pace with new threats and changes in emergency communications requirements If yes, please explain how often you revisit your assessment process and strategy, and give one example of a recent change you made based on those results. (Example: “We reprioritized our network monitoring tools after a mid-year review in July 2024.”) | F25: Recognized need; no action taken yet. | G25: NO
B27: 2. Identity, Authentication & Access Management
C28: A. Access Control Governance & Management
A29: 2A-1 | D29: 1. | E29: Does your organization have a formal governance group and approved policies that define who can create, change, or deactivate each type of account – user, administrative, service, and cloud – across all public safety systems? If yes, please name the governance body and explain where these policies are documented. (Example: “Our Identity Steering Committee owns the policy in our Security Manual, updated annually.") | F29: Partially implemented; improvements underway. | G29: IN PROGRESS
A30: 2A-2 | D30: 2. | E30: Are job roles, functions, and data classification levels officially documented, and do you regularly review granted permissions to make sure everyone has only the minimum access required (principle of least privilege)? If yes, please describe your review schedule and who conducts it. (Example: “We run quarterly access reports; managers verify roles in our IAM tool.”) | F30: Operational and tested. | G30: YES
A31: 2A-3 | D31: 3. | E31: Do your written policies require: * Strong authentication methods (e.g., complex passwords, hardware tokens, digital certificates, or biometrics) * A clear, auditable process for issuing, storing, and revoking credentials If yes, please list which authentication methods you use and how you track the full credential lifecycle. (Example: “We enforce 12-character passwords, issue YubiKeys for admin accounts, and record revocations in our ticketing system.”) | F31: Active effort in progress. | G31: IN PROGRESS
A32: 2A-4 | D32: 4. | E32: Do you perform account reviews and disable inactive or unnecessary accounts on a set schedule (e.g., every 30, 60, or 90 days), with clear assignment of responsibility for this task? If yes, please specify your schedule and the roles responsible for reviewing and deactivating accounts. (Example: “Every 60 days, IT Support runs an inactivity report, and the Security Manager approves deactivations.”) | F32: Being addressed through current initiatives. | G32: IN PROGRESS
A33: 2A-5 | D33: 5. | E33: Do your policies control remote or vendor/partner access by specifying: * Who is allowed to connect * Under what conditions (e.g., approved devices, time windows) * What monitoring or encryption is required If yes, please briefly outline these conditions and controls. (Example: “Remote logins require VPN with MFA; third-party sessions are logged and reviewed weekly.”) | F33: Absence acknowledged; not yet prioritized. | G33: NO
A34: 2A-6 | D34: 6. | E34: Do you have dedicated policies for service-based and cloud-based accounts that define: * Who “owns” each account * Its purpose and lifespan * What specific, limited privileges it needs * The method and frequency for reviewing these accounts If yes, please point to those policies and describe your review process. (Example: “Our Cloud Access Policy in Confluence; we audit service accounts monthly.”) | F34: Control is missing; flagged for remediation. | G34: NO
C36: B. Account & Credential Lifecycle Management
A37: 2B-1 | D37: 1. | E37: Do you have formal, written procedures – aligned with HR and operational teams – for how every account (user, remote, guest, temporary) is requested, approved, created, changed, and disabled? If yes, please say where these procedures are stored and how you keep them up to date. (Example: “Procedures are in our HR policy manual and IT operations guide; they’re reviewed annually by HR and IT leads.”) | F37: Implementation underway; on track. | G37: IN PROGRESS
A38: 2B-2 | D38: 2. | E38: Do you regularly review and adjust account permissions – especially upon change in an individual’s job role or their departure – to ensure each account has only the necessary access? If yes, please describe your review process and who is responsible. (Example: “Managers submit role change notices monthly; IT removes unneeded rights within 24 hours of notice.”) | F38: Configured and enforced. | G38: YES
A39: 2B-3 | D39: 3. | E39: Do your policies require: * Strong password rules (complexity, length) * Use of tokens or certificates where appropriate * Automated enforcement of these rules * Prompt rotation or revocation of credentials when compromised or upon personnel change If yes, please list the methods in place and how you track them. (Example: “Passwords must be 12+ characters and rotate every 90 days; admin accounts use YubiKeys; all revocations are logged in our ticketing system.”) | F39: Partially configured; finishing remaining steps. | G39: IN PROGRESS
A40: 2B-4 | D40: 4. | E40: Do you have a process for managing service and application accounts that includes: * Managing an up-to-date inventory? * Assigning each a unique identifier and granting only minimal required rights? * Monitoring or rotating their credentials on a regular schedule? If yes, please explain how you track these accounts and describe your credential rotation or monitoring schedule. (Example: “We list service accounts in our IAM tool and rotate their passwords every 60 days.”) | F40: Not applicable to current practice. | G40: NO
A41: 2B-5 | D41: 5. | E41: Do you use automated tools or scripts to detect accounts that haven’t been used for a defined period and automatically disable them on a set schedule? If yes, please describe the automation and schedule. (Example: “Accounts idle for 45 days are automatically disabled by our identity platform.”) | F41: Not yet implemented. | G41: NO
C43: C. Authentication & Credential Governance
A44: 2C-1 | D44: 1. | E44: Before granting any access, do you: * Verify each person’s identity using a documented process * Issue unique credentials for every user * Manage and document any cross-system trusts (certificates, SAML federation, etc.) If yes, please describe your identity verification steps and how you track trusted system relationships. (Example: “We check government ID and HR records before account creation; all certificate-based trusts are logged in our CMDB.”) | F44: Active and monitored. | G44: YES
A45: 2C-2 | D45: 2. | E45: Do your login screens and rules ensure that: * Error messages are vague enough to avoid revealing valid usernames * Accounts lock out or throttle after a set number of failed attempts * Failed logins and other anomalies are logged and monitored * Default vendor-supplied credentials are disabled before any system goes live If yes, please describe your lockout thresholds, logging practices, and how you disable defaults. (Example: “After 5 failed attempts, accounts lock for 15 minutes; all failures flow into SIEM alerts; we run a deployment script that removes default admin/password pairs.”) | F45: Completed and maintained. | G45: YES
A46: 2C-3 | D46: 3. | E46: Are there documented rules that specify: * Password complexity and minimum length * How often passwords must be changed * Secure storage protections (for example, hashing, vaulting) * Bans on weak, reused, or shared passwords If yes, please summarize your complexity and rotation requirements as well as technical enforcement controls. (Example: “Passwords must be ≥12 characters with letters, numbers, and symbols; rotated every 90 days; all hashes stored in our hardened vault.”) | F46: Implemented and documented. | G46: YES
A47: 2C-4 | D47: 4. | E47: Do your policies cover the use of password managers – requiring: * A strong master authentication factor (such as MFA) * Encryption of stored credentials * Use only on trusted, secured endpoints * Alignment with industry authentication standards If yes, please point to the policy section and note any approved tools or enforcement controls. (Example: “Our Access Policy mandates MFA on the vault and only allows approved browser extensions on corporate devices.”) | F47: Identified as a gap; not yet addressed. | G47: NO
A48: 2C-5 | D48: 5. | E48: Do you enforce multifactor authentication (MFA) for every user and access type – including remote, on-premises, and cloud environments – for both privileged and non-privileged accounts? If yes, please list which MFA methods you use and how you ensure they’re consistently enforced. (Example: “We require authenticator apps for all users; VPN and console logins both demand a one-time code.”) | F48: Controls are in place and verified. | G48: YES
C50: D. Authorization & Least Privilege Enforcement
A51: 2D-1 | D51: 1. | E51: Do you enforce the principle of least privilege for every account type – routine, temporary, privileged, and remote – so each has only the access required for its role, and review these permissions on a regular schedule? If yes, please describe how you enforce and review least privilege access controls. (Example: “Our IAM platform enforces least privilege automatically; managers get a quarterly report to approve or revoke rights.”) | F51: Work in progress toward full compliance. | G51: IN PROGRESS
A52: 2D-2 | D52: 2. | E52: Do you assign separate roles for key functions – such as system administration versus audit – to ensure no one person can both change and review the same settings or data? If yes, please describe which functions are separated and how you enforce this segregation of duties. (Example: “Sysadmin roles cannot access audit logs; auditors have read- only rights and are in a different user group.”) | F52: Process does not currently exist. | G52: NO
A53: 2D-3 | D53: 3. | E53: Are privileged accounts restricted to specific parts of your network or call/dispatch systems, continuously monitored for unauthorized data flows, and protected with stronger authentication controls? If yes, please outline your segmentation strategy and security monitoring configuration. (Example: “Admin consoles live on a separate VLAN; SIEM watches all privileged logins and flags cross-segment traffic.”) | F53: Currently being developed. | G53: IN PROGRESS
A54: 2D-4 | D54: 4. | E54: Do your systems check every access request against established roles and risk rules – so that sensitive information (caller details, medical data, law enforcement records) is only visible to authorized users – and log any anomalies? If yes, please explain how you define roles/risk levels and where logs of denied or anomalous access attempts are stored. (Example: “Our access gateway enforces role-based policies; all denials are sent to our audit log, reviewed weekly.”) | F54: No formal controls in place. | G54: NO
C56: E. Privileged Access Governance & Monitoring
A57: 2E-1 | D57: 1. | E57: Are all privileged users: * Uniquely identified and authenticated before gaining access * Required to acknowledge and follow enhanced behavior rules * Given specialized training and subject to accountability measures for misuse If yes, please summarize your identity checks, training program, and accountability process. (Example: “Privileged users complete an annual security training, sign our Administrator Code of Conduct, and any violations trigger our incident response protocol.”) | F57: Process is established and followed. | G57: YES
A58: 2E-2 | D58: 2. | E58: Do your policies specify how administrator accounts are: * Requested and formally approved * Tracked separately from standard user accounts * Decommissioned or removed when no longer needed If yes, please describe where these procedures are documented and how you track administrator accounts. (Example: “All admin requests go through our IT Change Board; we maintain a separate ‘Admin Accounts’ registry in our IAM tool and decommission via ticket when roles change.") | F58: Improvement efforts are ongoing. | G58: IN PROGRESS
A59: 2E-3 | D59: 3. | E59: Are sensitive interfaces – such as Session Border Controller (SBC) admin consoles and remote login portals – configured with: * Account lockout or throttling after failed attempts * Mandatory multifactor authentication If yes, please outline your lockout settings and MFA methods. (Example: “After 5 failed logins, the SBC locks for 30 minutes; remote VPN and console access require a hardware token plus PIN.”) | F59: Current status could not be confirmed. | G59: UNKNOWN
A60: 2E-4 | D60: 4. | E60: Do you regularly review and revoke unused or unnecessary elevated rights to prevent privilege creep and excessive access? If yes, please explain your review frequency and revocation process. (Example: “Quarterly, we run a report of all sudo-enabled accounts and remove rights for anyone who hasn’t used them in 60 days.”) | F60: Working to formalize this process. | G60: IN PROGRESS
A61: 2E-5 | D61: 5. | E61: Do you record and monitor all privileged user sessions, and review those logs for misuse, unauthorized escalation, or anomalous activity? If yes, please describe your logging system and review cadence. (Example: “All CLI sessions are captured in our centralized logging server; Security reviews high-risk session logs weekly.”) | F61: Not currently in scope; noted as a gap. | G61: NO
C63: F. Session Management & Monitoring
A64: 2F-1 | D64: 1. | E64: Before starting any session – including remote connections – do you verify and authenticate each user so every session can be traced back to a single individual? If yes, please explain how you ensure individual user identification (for example, shared accounts vs. individual accounts). (Example: “We prohibit shared credentials; every user logs in with their personal SSO credentials and MFA.”) | F64: This has not been established. | G64: NO
A65: 2F-2 | D65: 2. | E65: Do you configure systems to automatically lock or terminate user sessions after a defined period of inactivity – based on your operational requirements – to prevent access at unattended workstations or devices? If yes, please state your configured inactivity timeouts and describe how they are technically enforced. (Example: “Workstations lock after 10 minutes idle; remote desktops disconnect after 15 minutes.") | F65: Documentation is in development. | G65: IN PROGRESS
A66: 2F-3 | D66: 3. | E66: Do you require users to reauthenticate – or explicitly resume – a session before continuing certain activities or after a set duration, with stronger rules for higher-risk operations? If yes, please describe which actions or time thresholds trigger session reauthentication. (Example: “Access to financial records prompts reauthentication every 30 minutes; other actions require it only after 4 hours.”) | F66: Partially implemented; improvements underway. | G66: IN PROGRESS
A67: 2F-4 | D67: 4. | E67: Do your policies and systems prevent unauthorized access by: * Locking devices when idle or upon network disconnect * Restricting remote sessions from operating on unverified or shared endpoints * Terminating sessions upon connection loss or periodic checks fail If yes, please outline the controls for both physical workstations and remote devices. (Example: “Workstation screensaver locks on idle; remote sessions enforce device attestation and disconnect on VPN drop.”) | F67: Active effort in progress. | G67: IN PROGRESS
A68: 2F-5 | D68: 5. | E68: Do you record and review all session events – successful logins, failed attempts, and privilege changes – and generate alerts for unusual behavior (such as logins at odd hours or unexpected data transfers)? If yes, please describe your logging and alerting setup. (Example: “All events feed into our SIEM; we have alerts for logins outside 8 AM–6 PM and data exports over 1 GB.”) | F68: Being addressed through current initiatives. | G68: IN PROGRESS
B70: 3. Data Security & Lifecycle Management
C71: A. Data Classification & Labeling
A72: 3A-1 | D72: 1. | E72: Has your designated data governance group formally: * Defined data classification levels (for example, Public, Internal, Confidential) * Set default labels on new or incoming data * Integrated those labels into system design and workflows * Reviewed and updated labels when data is transferred across departments or to external partners If yes, please describe how the governance body assigns and updates labels. (Example: “Our Data Governance Board applies ‘Confidential’ by default to all vendor-supplied files; whenever data is shared outside the department, they review and adjust labels quarterly.”) | F72: Recognized need; no action taken yet. | G72: NO
A73: 3A-2 | D73: 2. | E73: Do your user accounts and system policies automatically enforce controls based on data labels – such as blocking access or preventing actions that exceed a user’s clearance level? If yes, please explain which systems enforce these controls and how access mismatches are detected and handled. (Example: “Our document portal checks user roles against file labels and denies downloads if clearance is too low, logging every denied attempt.”) | F73: Absence acknowledged; not yet prioritized. | G73: NO
A74: 3A-3 | D74: 3. | E74: Do you have procedures to ensure that any external data you receive is: * Classified upon receipt * Stored and used in line with its label’s handling requirements * Retained or disposed of according to defined retention schedules If yes, please outline how incoming data is classified, stored, and tracked. (Example: “All third-party incident reports are tagged ‘Internal’ on upload; we archive them for two years and then purge automatically via our records system.”) | F74: Practice is mature and consistent. | G74: YES
C76: B. Data Protection & Lifecycle Management
A77: 3B-1 | D77: 1. | E77: Do you maintain a formal inventory that maps each data classification (for example, Public, Internal, Confidential) to its required handling, retention period, protection measures, and how updates affect systems throughout the data’s lifecycle? If yes, please explain where this inventory is stored and how it’s maintained and kept current. (Example: “Our data inventory lives in the CMDB; it links each data type to its retention schedule, classification controls, and update-impact rules, and is reviewed annually.”) | F77: Implementation underway; on track. | G77: IN PROGRESS
A78: 3B-2 | D78: 2. | E78: Do you encrypt all sensitive data at rest – including on-premises and cloud storage, logs, recordings, and backups – using securely generated, stored, rotated, and access-controlled keys, and ensure your service providers meet these standards? If yes, please list your encryption tools, key-management processes, and any provider compliance (e.g., FedRAMP, SOC 2). (Example: “We use AES-256 via HSM-backed key vaults; keys rotate quarterly; our cloud storage is FedRAMP Moderate certified.”) | F78: On the roadmap for upcoming period. | G78: PLANNED
A79: 3B-3 | D79: 3. | E79: Do your procedures require secure transfer protocols, physical controls, and media sanitization or destruction based on data classification – automatically blocking or logging unauthorized actions? If yes, please describe how these controls are implemented and enforced. (Example: “All Confidential files transfer over SFTP; labeled printers enforce print restrictions; disposal scripts zero-fill disks and purge print trays automatically.”) | F79: Planned but not yet started. | G79: PLANNED
A80: 3B-4 | D80: 4. | E80: Are backup tapes, external drives, printed reports, and other physical media stored, transported, and accessed only by authorized personnel based on its classification – tracked, encrypted where required, and secured in designated areas? If yes, please describe your storage, tracking, and encryption processes. (Example: “All external drives are AES-256 encrypted and logged in our media register; backup tapes are locked in an approved safe and access is badge-controlled.”) | F80: Partially configured; finishing remaining steps. | G80: IN PROGRESS
A81: 3B-5 | D81: 5. | E81: Do you classify your logs and monitoring outputs, store them according to operational and regulatory retention requirements, and securely dispose of or destroy them when no longer needed? If yes, please outline your log classification scheme, retention periods, and disposal methods. (Example: “Audit logs tagged Internal are kept 90 days online, then archived for one year; expired archives are shredded or cryptographically wiped.”) | F81: Control is missing; flagged for remediation. | G81: NO
A82: 3B-6 | D82: 6. | E82: Do you mark hardware and software components in your inventory for end-of-life, then sanitize or destroy them in accordance with your data protection and classification policies? If yes, please explain your decommissioning process and how it aligns with classification rules. (Example: “Decommissioned servers are tagged ‘Decom’; drives undergo DoD 5220.22-M wipe, and certificates of destruction are filed.”) | F82: Work in progress toward full compliance. | G82: IN PROGRESS
C84: C. Data Access Monitoring & Disclosure Management
A85: 3C-1 | D85: 1. | E85: Do you have documented controls and workflows that define: * Who can approve sharing sensitive data * Which risk factors to consider (for example, recipient, data classification, legal requirements) * How to securely transmit or share the data once approved If yes, please outline your approval process and secure sharing methods. (Example: “Disclosures require a manager’s sign‐off in our Records System; approved files go via encrypted email or secure portal.”) | F85: Fully implemented per current policy. | G85: YES
A86: 3C-2 | D86: 2. | E86: Are there formal procedures to detect, contain, and remediate any unauthorized data spill – so you can quickly respond, investigate, and restore secure operations? If yes, please summarize your incident response steps and team roles. (Example: “Our Data Response Plan triggers alerts on large exports; the InfoSec team isolates affected systems and runs a root‐cause analysis within 24 hours.”) | F86: Currently being developed. | G86: IN PROGRESS
A87: 3C-3 | D87: 3. | E87: Do you log every access to or attempted disclosure of sensitive data – capturing details like who accessed it, when, from where, and what was done – and keep those logs long enough to support audits and investigations? If yes, please describe your logging system, retention period, and the key fields captured in each log. (Example: “All data‐access events feed into our SIEM with user ID, timestamp, source IP, and action type; logs are retained for two years.”) | F87: Improvement efforts are ongoing. | G87: IN PROGRESS
B89: 4. Network & Communications Governance
C90: A. Network Infrastructure & Boundary Controls
A91: 4A-1 | D91: 1. | E91: Have you designed and formally documented network segmentation using: * Enforced access controls (ACLs, firewalls) * Logical or physical partitions (VLANs, separate switches) * Restrictions on peer-to-peer communications If yes, please outline your segmentation model and where and how documentation is maintained. (Example: “Our network diagram shows VLANs for voice, dispatch, and admin; ACLs block inter-VLAN traffic except via a central firewall.”) | F91: Working to formalize this process. | G91: IN PROGRESS
A92: 4A-2 | D92: 2. | E92: Do you configure all perimeter devices – like Session Border Controllers, cross-network gateways, and other edge appliances – with: * A default-deny policy for signaling and media flows * Least-privilege rules that only allow explicitly approved endpoints and port usage * Continuous logging and alerting for any unauthorized or suspicious connection attempts If yes, please describe your default-deny flow rules, how you enforce least-privilege access, and which monitoring tools you use to detect anomalies. (Example: “Our SBCs only permit SIP traffic on ports 5060–5061 from known IP ranges; all other attempts are dropped and forwarded to our SIEM for real-time alerting.") | F92: Documentation is in development. | G92: IN PROGRESS
A93: 4A-3 | D93: 3. | E93: Do you maintain demilitarized zones (DMZs) and isolated network segments using: * Deny-by-default firewall rules * Controlled ingress and egress filtering * Layered defenses (IDS/IPS, web proxies) * Strict separation of public-facing services from core systems If yes, please explain your DMZ design and enforcement strategies. (Example: “All web servers live in a DMZ with no direct access to the internal network; traffic passes through a reverse proxy and is inspected by an IPS.”) | F93: In place; reviewed periodically. | G93: YES
A94: 4A-4 | D94: 4. | E94: Do you secure and monitor devices that connect to more than one network (for example, cross-network gateways) so that: * Configuration settings prevent data leakage and unauthorized changes * All access and changes are logged * Alerts are generated for suspicious activity If yes, please describe your hardening standards, logging practices, and monitoring tools. (Example: “We apply CIS Benchmarks on all multi-homed routers, forward their syslogs to our SIEM, and use automated scans to detect config drift.”) | F94: Partially implemented; improvements underway. | G94: IN PROGRESS
A95: 4A-5 | D95: 5. | E95: Do you further segment and monitor internal connections – between applications, databases, and system components – to ensure only approved traffic flows and to limit breach impact? If yes, please describe your micro-segmentation and internal traffic control strategy. (Example: “Our micro-segmentation policy uses host-based firewalls to allow only service-specific ports; any deviation triggers an alert.”) | F95: Active effort in progress. | G95: IN PROGRESS
C97: B. Network Traffic & Threat Controls
A98: 4B-1 | D98: 1. | E98: Does your overall network design layer multiple defenses – segmentation, endpoint protection, encryption in transit, input validation/scanning at all entry points – to block and contain threats? If yes, please summarize your defense-in-depth architecture and supporting technologies. (Example: “We combine micro-segmentation, host-based firewalls, TLS encryption for all services, and an IDS at each network boundary.”) | F98: Being addressed through current initiatives. | G98: IN PROGRESS
A99: 4B-2 | D99: 2. | E99: Do you configure firewalls, proxies, segmentation boundaries, and routing rules to block all traffic by default – only allowing trusted devices and systems – and monitor for any policy violations? If yes, please describe your default-deny configuration and traffic monitoring approach. (Example: “All firewall zones start with deny-all; we maintain allow-lists per zone and forward denied attempts to our SIEM for review.”) | F99: Budgeted and scheduled. | G99: PLANNED
A100: 4B-3 | D100: 3. | E100: Are critical services – such as GIS servers and call-routing platforms – kept separate (either on their own networks or VLANs) from general-use systems and protected with multiple access barriers? If yes, please outline how you isolate and protect these critical systems. (Example: “Our GIS cluster is on a dedicated VLAN behind a hardened firewall; only dispatch consoles can reach it over a dedicated VPN.”) | F100: Implementation underway; on track. | G100: IN PROGRESS
A101: 4B-4 | D101: 4. | E101: Do you disable or tightly manage any direct device-to-device connections – logging, monitoring, and validating them – to prevent unauthorized or malicious file or data exchanges? If yes, please explain how you govern peer-to-peer communications and manage exceptions. (Example: “We block all SMB between endpoints; approved file shares run through our secure file-transfer service, which logs every transfer.”) | F101: Not applicable to current practice. | G101: NO
A102: 4B-5 | D102: 5. | E102: Do you employ rate limiting, traffic filtering, and shaping at key ingress and egress points to guard against denial-of-service and other resource exhaustion attacks – and test these controls regularly? If yes, please describe your DoS defenses and how frequently they are tested. (Example: “Our edge routers enforce per-IP rate limits; quarterly, we run simulated DoS tests to verify thresholds and alerts.”) | F102: Target date established; not yet begun. | G102: PLANNED
C104: C. DNS Governance & Security Controls
A105: 4C-1 | D105: 1. | E105: Is your DNS environment designed so that authoritative and recursive services are separated, and do you implement DNSSEC or encrypted DNS (DoH/DoT) to guard against attacks like cache poisoning or DDoS? If yes, please describe your service segmentation and protective DNS technologies. (Example: “Authoritative and recursive servers run on distinct subnets; we’ve enabled DNSSEC signing and force DoH for client queries.”) | F105: Not yet implemented. | G105: NO
A106: 4C-2 | D106: 2. | E106: Do you have written governance for DNS administration that: * Restricts who can manage DNS roles (e.g., zone admins, record owners) * Enforces access controls and approval workflows for any DNS changes * Requires logged reviews or signoffs for all record or zone modifications If yes, please describe your governance body and change-approval process. (Example: “Our Network Change Board approves all DNS changes; only designated DNS admins can modify records, and each change is recorded in our ticketing system.”) | F106: Identified as a gap; not yet addressed. | G106: NO
A107: 4C-3 | D107: 3. | E107: Do you enforce a secure configuration baseline for DNS servers that: * Disables unused or risky features * Requires change-control procedures for any configuration updates * Validates inputs (e.g., record formats) to prevent tampering or injection attacks If yes, please point to your baseline documentation and describe how configuration changes are managed. (Example: “We apply our DNS CIS Benchmark baseline via automation; any deviation triggers a config-drift alert and requires peer review to remediate.”) | F107: Process does not currently exist. | G107: NO
A108: 4C-4 | D108: 4. | E108: Do your policies require that any user with elevated DNS privileges (zone admins, change operators) authenticate with strong methods – such as MFA or client certificates – and that remote management access is tightly limited, logged, and audited? If yes, please list the authentication methods used and how remote access is controlled. (Example: “All DNS admins log in via SSO with MFA; remote console access is only allowed from a jump server and is recorded in our audit logs.”) | F108: No formal controls in place. | G108: NO
A109: 4C-5 | D109: 5. | E109: Do you apply security updates and patches to DNS server software as soon as they’re available – following a documented patch-management schedule? If yes, please outline your patch cadence and how you verify completion. (Example: “We run a monthly patch cycle; DNS servers are updated in our test lab first, then pushed to production during a maintenance window, with compliance reports generated afterward.”) | F109: Partially configured; finishing remaining steps. | G109: IN PROGRESS
A110: 4C-6 | D110: 6. | E110: Do you capture and retain logs for every DNS query, configuration change, and zone update – with enough detail (user, timestamp, action) – and integrate those logs into your SIEM or review them regularly for threats? If yes, please explain your logging detail, retention period, and review process. (Example: “Our DNS servers log queries and updates to syslog with user IDs; logs are ingested into our SIEM and reviewed weekly for anomalies.”) | F110: Information not available at time of assessment. | G110: UNKNOWN
C112: D. Email System Security & Threat Protection
A113: 4D-1 | D113: 1. | E113: Is your email system kept separate from your core, real-time operations (for example, 9-1-1 consoles), and treated as a semi-trusted network – subject to traffic inspection, sandboxing, or other protections? If yes, please explain how you isolate email traffic, and which inspection or sandboxing tools are used. (Example: “Email servers run on a separate VLAN with a mail-proxy appliance that sandboxes attachments.”) | F113: Operational and tested. | G113: YES
A114: 4D-2 | D114: 2. | E114: Do you set up all email servers and user email apps according to an approved “hardened” checklist, and do you regularly review key security settings (e.g., DKIM, SPF, DMARC, TLS)? If yes, please list where your baseline hardening checklist is documented and how often you audit those settings. (Example: “Our checklist is in Confluence; we run automated compliance scans every month.”) | F114: Not applicable to this environment. | G114: NOT APPLICABLE
A115: 4D-3 | D115: 3. | E115: Can only approved, trained staff perform email tasks like: * Delegating someone else’s mailbox * Creating or changing inbox rules (automatic forwards, filters) If yes, please describe how you assign and track those permissions. (Example: “Only our Messaging Admin group can change mailbox rules; we review their access quarterly.”) | F115: Configured and enforced. | G115: YES
A116: 4D-4 | D116: 4. | E116: Do you scan all incoming and outgoing email for malicious attachments, links, or code, and do you have continuous monitoring that blocks or flags phishing and other anomalies? If yes, please name the tools or services you use and describe your monitoring and alerting process. (Example: “We use SecureMail Gateway for real-time scanning and SIEM alerts on any flagged messages.”) | F116: Active and monitored. | G116: YES
...

Sheet Full Score Table
D2: # of Questions | E2: Not Applicable | F2: Unknown | G2: No (0) | H2: Planned (1) | I2: In Progress (2) | J2: Yes (3) | K2: Total | L2: out of | M2: Possible
C3: Overall Total | D3: 198 | E3: =N(E8)+N(E15)+N(E19)+N(E26)+N(E31)+N(E35)+N(E40)+N(E44)+N(E49)+N(E55)+N(E60)+N(E63)+N(E67) -> 9 | F3: =N(F8)+N(F15)+N(F19)+N(F26)+N(F31)+N(F35)+N(F40)+N(F44)+N(F49)+N(F55)+N(F60)+N(F63)+N(F67) -> 7 | G3: =N(G8)+N(G15)+N(G19)+N(G26)+N(G31)+N(G35)+N(G40)+N(G44)+N(G49)+N(G55)+N(G60)+N(G63)+N(G67) -> 72 | H3: =N(H8)+N(H15)+N(H19)+N(H26)+N(H31)+N(H35)+N(H40)+N(H44)+N(H49)+N(H55)+N(H60)+N(H63)+N(H67) -> 15 | I3: =N(I8)+N(I15)+N(I19)+N(I26)+N(I31)+N(I35)+N(I40)+N(I44)+N(I49)+N(I55)+N(I60)+N(I63)+N(I67) -> 55 | J3: =N(J8)+N(J15)+N(J19)+N(J26)+N(J31)+N(J35)+N(J40)+N(J44)+N(J49)+N(J55)+N(J60)+N(J63)+N(J67) -> 40 | K3: =N(H3)+(N(I3)*2)+(N(J3)*3) -> 245 | L3: of | M3: =(SUM(F3:J3)*3) -> 567
B4: Governance, Risk & Strategy | C4: Executive Leadership & Resource Allocation | D4: 3 | E4: =_xlfn.LET(_xlpm.na,COUNTIF('Question Set'!$G$4:$G$6,"Not Applicable"),IF(_xlpm.na=0,"-",_xlpm.na)) -> - | F4: =_xlfn.LET(_xlpm.u,COUNTIF('Question Set'!$G$4:$G$6,"Unknown"),IF(_xlpm.u=0,"-",_xlpm.u)) -> - | G4: =_xlfn.LET(_xlpm.n,COUNTIF('Question Set'!$G$4:$G$6,"No"),IF(_xlpm.n=0,"-",_xlpm.n)) -> - | H4: =_xlfn.LET(_xlpm.pl,COUNTIF('Question Set'!$G$4:$G$6,"Planned"),IF(_xlpm.pl=0,"-",_xlpm.pl)) -> 1 | I4: =_xlfn.LET(_xlpm.ip,COUNTIF('Question Set'!$G$4:$G$6,"In Progress"),IF(_xlpm.ip=0,"-",_xlpm.ip)) -> - | J4: =_xlfn.LET(_xlpm.y,COUNTIF('Question Set'!$G$4:$G$6,"Yes"),IF(_xlpm.y=0,"-",_xlpm.y)) -> 2 | K4: =N(H4)+(N(I4)*2)+(N(J4)*3) -> 7 | L4: of | M4: =(SUM(F4:J4)*3) -> 9
C5: Policy & Asset Inventory Management | D5: 3 | E5: =_xlfn.LET(_xlpm.na,COUNTIF('Question Set'!$G$9:$G$11,"Not Applicable"),IF(_xlpm.na=0,"-",_xlpm.na)) -> - | F5: =_xlfn.LET(_xlpm.u,COUNTIF('Question Set'!$G$9:$G$11,"Unknown"),IF(_xlpm.u=0,"-",_xlpm.u)) -> - | G5: =_xlfn.LET(_xlpm.n,COUNTIF('Question Set'!$G$9:$G$11,"No"),IF(_xlpm.n=0,"-",_xlpm.n)) -> 2 | H5: =_xlfn.LET(_xlpm.pl,COUNTIF('Question Set'!$G$9:$G$11,"Planned"),IF(_xlpm.pl=0,"-",_xlpm.pl)) -> - | I5: =_xlfn.LET(_xlpm.ip,COUNTIF('Question Set'!$G$9:$G$11,"In Progress"),IF(_xlpm.ip=0,"-",_xlpm.ip)) -> - | J5: =_xlfn.LET(_xlpm.y,COUNTIF('Question Set'!$G$9:$G$11,"Yes"),IF(_xlpm.y=0,"-",_xlpm.y)) -> 1 | K5: =N(H5)+(N(I5)*2)+(N(J5)*3) -> 3 | L5: of | M5: =(SUM(F5:J5)*3) -> 9
C6: Role Definition & Governance Oversight | D6: 5 | E6: =_xlfn.LET(_xlpm.na,COUNTIF('Question Set'!$G$14:$G$18,"Not Applicable"),IF(_xlpm.na=0,"-",_xlpm.na)) -> - | F6: =_xlfn.LET(_xlpm.u,COUNTIF('Question Set'!$G$14:$G$18,"Unknown"),IF(_xlpm.u=0,"-",_xlpm.u)) -> - | G6: =_xlfn.LET(_xlpm.n,COUNTIF('Question Set'!$G$14:$G$18,"No"),IF(_xlpm.n=0,"-",_xlpm.n)) -> 1 | H6: =_xlfn.LET(_xlpm.pl,COUNTIF('Question Set'!$G$14:$G$18,"Planned"),IF(_xlpm.pl=0,"-",_xlpm.pl)) -> - | I6: =_xlfn.LET(_xlpm.ip,COUNTIF('Question Set'!$G$14:$G$18,"In Progress"),IF(_xlpm.ip=0,"-",_xlpm.ip)) -> 1 | J6: =_xlfn.LET(_xlpm.y,COUNTIF('Question Set'!$G$14:$G$18,"Yes"),IF(_xlpm.y=0,"-",_xlpm.y)) -> 3 | K6: =N(H6)+(N(I6)*2)+(N(J6)*3) -> 11 | L6: of | M6: =(SUM(F6:J6)*3) -> 15
C7: Risk Assessment & Management Strategy | D7: 5 | E7: =_xlfn.LET(_xlpm.na,COUNTIF('Question Set'!$G$21:$G$25,"Not Applicable"),IF(_xlpm.na=0,"-",_xlpm.na)) -> - | F7: =_xlfn.LET(_xlpm.u,COUNTIF('Question Set'!$G$21:$G$25,"Unknown"),IF(_xlpm.u=0,"-",_xlpm.u)) -> - | G7: =_xlfn.LET(_xlpm.n,COUNTIF('Question Set'!$G$21:$G$25,"No"),IF(_xlpm.n=0,"-",_xlpm.n)) -> 4 | H7: =_xlfn.LET(_xlpm.pl,COUNTIF('Question Set'!$G$21:$G$25,"Planned"),IF(_xlpm.pl=0,"-",_xlpm.pl)) -> - | I7: =_xlfn.LET(_xlpm.ip,COUNTIF('Question Set'!$G$21:$G$25,"In Progress"),IF(_xlpm.ip=0,"-",_xlpm.ip)) -> 1 | J7: =_xlfn.LET(_xlpm.y,COUNTIF('Question Set'!$G$21:$G$25,"Yes"),IF(_xlpm.y=0,"-",_xlpm.y)) -> - | K7: =N(H7)+(N(I7)*2)+(N(J7)*3) -> 2 | L7: of | M7: =(SUM(F7:J7)*3) -> 15
C8: Domain Total | D8: =SUM(D4:D7) -> 16 | E8: =_xlfn.LET(_xlpm.x,(SUM(E4:E7)),IF(_xlpm.x=0,"-",_xlpm.x)) -> - | F8: =_xlfn.LET(_xlpm.x,(SUM(F4:F7)),IF(_xlpm.x=0,"-",_xlpm.x)) -> - | G8: =_xlfn.LET(_xlpm.x,(SUM(G4:G7)),IF(_xlpm.x=0,"-",_xlpm.x)) -> 7 | H8: =_xlfn.LET(_xlpm.x,(SUM(H4:H7)),IF(_xlpm.x=0,"-",_xlpm.x)) -> 1 | I8: =_xlfn.LET(_xlpm.x,(SUM(I4:I7)),IF(_xlpm.x=0,"-",_xlpm.x)) -> 2 | J8: =_xlfn.LET(_xlpm.x,(SUM(J4:J7)),IF(_xlpm.x=0,"-",_xlpm.x)) -> 6 | K8: =N(H8)+(N(I8)*2)+(N(J8)*3) -> 23 | L8: of | M8: =(SUM(F8:J8)*3) -> 48
B9: Identity, Authentication & Access Management | C9: Access Control Governance & Management | D9: 6 | E9: =_xlfn.LET(_xlpm.na,COUNTIF('Question Set'!$G$29:$G$34,"Not Applicable"),IF(_xlpm.na=0,"-",_xlpm.na)) -> - | F9: =_xlfn.LET(_xlpm.u,COUNTIF('Question Set'!$G$29:$G$34,"Unknown"),IF(_xlpm.u=0,"-",_xlpm.u)) -> - | G9: =_xlfn.LET(_xlpm.n,COUNTIF('Question Set'!$G$29:$G$34,"No"),IF(_xlpm.n=0,"-",_xlpm.n)) -> 2 | H9: =_xlfn.LET(_xlpm.pl,COUNTIF('Question Set'!$G$29:$G$34,"Planned"),IF(_xlpm.pl=0,"-",_xlpm.pl)) -> - | I9: =_xlfn.LET(_xlpm.ip,COUNTIF('Question Set'!$G$29:$G$34,"In Progress"),IF(_xlpm.ip=0,"-",_xlpm.ip)) -> 3 | J9: =_xlfn.LET(_xlpm.y,COUNTIF('Question Set'!$G$29:$G$34,"Yes"),IF(_xlpm.y=0,"-",_xlpm.y)) -> 1 | K9: =N(H9)+(N(I9)*2)+(N(J9)*3) -> 9 | L9: of | M9: =(SUM(F9:J9)*3) -> 18
C10: Account & Credential Lifecycle Management | D10: 5 | E10: =_xlfn.LET(_xlpm.na,COUNTIF('Question Set'!$G$37:$G$41,"Not Applicable"),IF(_xlpm.na=0,"-",_xlpm.na)) -> - | F10: =_xlfn.LET(_xlpm.u,COUNTIF('Question Set'!$G$37:$G$41,"Unknown"),IF(_xlpm.u=0,"-",_xlpm.u)) -> - | G10: =_xlfn.LET(_xlpm.n,COUNTIF('Question Set'!$G$37:$G$41,"No"),IF(_xlpm.n=0,"-",_xlpm.n)) -> 2 | H10: =_xlfn.LET(_xlpm.pl,COUNTIF('Question Set'!$G$37:$G$41,"Planned"),IF(_xlpm.pl=0,"-",_xlpm.pl)) -> - | I10: =_xlfn.LET(_xlpm.ip,COUNTIF('Question Set'!$G$37:$G$41,"In Progress"),IF(_xlpm.ip=0,"-",_xlpm.ip)) -> 2 | J10: =_xlfn.LET(_xlpm.y,COUNTIF('Question Set'!$G$37:$G$41,"Yes"),IF(_xlpm.y=0,"-",_xlpm.y)) -> 1 | K10: =N(H10)+(N(I10)*2)+(N(J10)*3) -> 7 | L10: of | M10: =(SUM(F10:J10)*3) -> 15
C11: Authentication & Credential Governance | D11: 5 | E11: =_xlfn.LET(_xlpm.na,COUNTIF('Question Set'!$G$44:$G$48,"Not Applicable"),IF(_xlpm.na=0,"-",_xlpm.na)) -> - | F11: =_xlfn.LET(_xlpm.u,COUNTIF('Question Set'!$G$44:$G$48,"Unknown"),IF(_xlpm.u=0,"-",_xlpm.u)) -> - | G11: =_xlfn.LET(_xlpm.n,COUNTIF('Question Set'!$G$44:$G$48,"No"),IF(_xlpm.n=0,"-",_xlpm.n)) -> 1 | H11: =_xlfn.LET(_xlpm.pl,COUNTIF('Question Set'!$G$44:$G$48,"Planned"),IF(_xlpm.pl=0,"-",_xlpm.pl)) -> - | I11: =_xlfn.LET(_xlpm.ip,COUNTIF('Question Set'!$G$44:$G$48,"In Progress"),IF(_xlpm.ip=0,"-",_xlpm.ip)) -> - | J11: =_xlfn.LET(_xlpm.y,COUNTIF('Question Set'!$G$44:$G$48,"Yes"),IF(_xlpm.y=0,"-",_xlpm.y)) -> 4 | K11: =N(H11)+(N(I11)*2)+(N(J11)*3) -> 12 | L11: of | M11: =(SUM(F11:J11)*3) -> 15
C12: Authorization & Least Privilege Enforcement | D12: 4 | E12: =_xlfn.LET(_xlpm.na,COUNTIF('Question Set'!$G$51:$G$54,"Not Applicable"),IF(_xlpm.na=0,"-",_xlpm.na)) -> - | F12: =_xlfn.LET(_xlpm.u,COUNTIF('Question Set'!$G$51:$G$54,"Unknown"),IF(_xlpm.u=0,"-",_xlpm.u)) -> - | G12: =_xlfn.LET(_xlpm.n,COUNTIF('Question Set'!$G$51:$G$54,"No"),IF(_xlpm.n=0,"-",_xlpm.n)) -> 2 | H12: =_xlfn.LET(_xlpm.pl,COUNTIF('Question Set'!$G$51:$G$54,"Planned"),IF(_xlpm.pl=0,"-",_xlpm.pl)) -> - | I12: =_xlfn.LET(_xlpm.ip,COUNTIF('Question Set'!$G$51:$G$54,"In Progress"),IF(_xlpm.ip=0,"-",_xlpm.ip)) -> 2 | J12: =_xlfn.LET(_xlpm.y,COUNTIF('Question Set'!$G$51:$G$54,"Yes"),IF(_xlpm.y=0,"-",_xlpm.y)) -> - | K12: =N(H12)+(N(I12)*2)+(N(J12)*3) -> 4 | L12: of | M12: =(SUM(F12:J12)*3) -> 12
C13: Privileged Access Governance & Monitoring | D13: 5 | E13: =_xlfn.LET(_xlpm.na,COUNTIF('Question Set'!$G$57:$G$61,"Not Applicable"),IF(_xlpm.na=0,"-",_xlpm.na)) -> - | F13: =_xlfn.LET(_xlpm.u,COUNTIF('Question Set'!$G$57:$G$61,"Unknown"),IF(_xlpm.u=0,"-",_xlpm.u)) -> 1 | G13: =_xlfn.LET(_xlpm.n,COUNTIF('Question Set'!$G$57:$G$61,"No"),IF(_xlpm.n=0,"-",_xlpm.n)) -> 1 | H13: =_xlfn.LET(_xlpm.pl,COUNTIF('Question Set'!$G$57:$G$61,"Planned"),IF(_xlpm.pl=0,"-",_xlpm.pl)) -> - | I13: =_xlfn.LET(_xlpm.ip,COUNTIF('Question Set'!$G$57:$G$61,"In Progress"),IF(_xlpm.ip=0,"-",_xlpm.ip)) -> 2 | J13: =_xlfn.LET(_xlpm.y,COUNTIF('Question Set'!$G$57:$G$61,"Yes"),IF(_xlpm.y=0,"-",_xlpm.y)) -> 1 | K13: =N(H13)+(N(I13)*2)+(N(J13)*3) -> 7 | L13: of | M13: =(SUM(F13:J13)*3) -> 15
C14: Session Management & Monitoring | D14: 5 | E14: =_xlfn.LET(_xlpm.na,COUNTIF('Question Set'!$G$64:$G$68,"Not Applicable"),IF(_xlpm.na=0,"-",_xlpm.na)) -> - | F14: =_xlfn.LET(_xlpm.u,COUNTIF('Question Set'!$G$64:$G$68,"Unknown"),IF(_xlpm.u=0,"-",_xlpm.u)) -> - | G14: =_xlfn.LET(_xlpm.n,COUNTIF('Question Set'!$G$64:$G$68,"No"),IF(_xlpm.n=0,"-",_xlpm.n)) -> 1 | H14: =_xlfn.LET(_xlpm.pl,COUNTIF('Question Set'!$G$64:$G$68,"Planned"),IF(_xlpm.pl=0,"-",_xlpm.pl)) -> - | I14: =_xlfn.LET(_xlpm.ip,COUNTIF('Question Set'!$G$64:$G$68,"In Progress"),IF(_xlpm.ip=0,"-",_xlpm.ip)) -> 4 | J14: =_xlfn.LET(_xlpm.y,COUNTIF('Question Set'!$G$64:$G$68,"Yes"),IF(_xlpm.y=0,"-",_xlpm.y)) -> - | K14: =N(H14)+(N(I14)*2)+(N(J14)*3) -> 8 | L14: of | M14: =(SUM(F14:J14)*3) -> 15
C15: Domain Total | D15: =SUM(D9:D14) -> 30 | E15: =_xlfn.LET(_xlpm.x,(SUM(E9:E14)),IF(_xlpm.x=0,"-",_xlpm.x)) -> - | F15: =_xlfn.LET(_xlpm.x,(SUM(F9:F14)),IF(_xlpm.x=0,"-",_xlpm.x)) -> 1 | G15: =_xlfn.LET(_xlpm.x,(SUM(G9:G14)),IF(_xlpm.x=0,"-",_xlpm.x)) -> 9 | H15: =_xlfn.LET(_xlpm.x,(SUM(H9:H14)),IF(_xlpm.x=0,"-",_xlpm.x)) -> - | I15: =_xlfn.LET(_xlpm.x,(SUM(I9:I14)),IF(_xlpm.x=0,"-",_xlpm.x)) -> 13 | J15: =_xlfn.LET(_xlpm.x,(SUM(J9:J14)),IF(_xlpm.x=0,"-",_xlpm.x)) -> 7 | K15: =N(H15)+(N(I15)*2)+(N(J15)*3) -> 47 | L15: of | M15: =(SUM(F15:J15)*3) -> 90
B16: Data Security & Lifecycle Management | C16: Data Classification & Labeling | D16: 3 | E16: =_xlfn.LET(_xlpm.na,COUNTIF('Question Set'!$G$72:$G$74,"Not Applicable"),IF(_xlpm.na=0,"-",_xlpm.na)) -> - | F16: =_xlfn.LET(_xlpm.u,COUNTIF('Question Set'!$G$72:$G$74,"Unknown"),IF(_xlpm.u=0,"-",_xlpm.u)) -> - | G16: =_xlfn.LET(_xlpm.n,COUNTIF('Question Set'!$G$72:$G$74,"No"),IF(_xlpm.n=0,"-",_xlpm.n)) -> 2 | H16: =_xlfn.LET(_xlpm.pl,COUNTIF('Question Set'!$G$72:$G$74,"Planned"),IF(_xlpm.pl=0,"-",_xlpm.pl)) -> - | I16: =_xlfn.LET(_xlpm.ip,COUNTIF('Question Set'!$G$72:$G$74,"In Progress"),IF(_xlpm.ip=0,"-",_xlpm.ip)) -> - | J16: =_xlfn.LET(_xlpm.y,COUNTIF('Question Set'!$G$72:$G$74,"Yes"),IF(_xlpm.y=0,"-",_xlpm.y)) -> 1 | K16: =N(H16)+(N(I16)*2)+(N(J16)*3) -> 3 | L16: of | M16: =(SUM(F16:J16)*3) -> 9
C17: Data Protection & Lifecycle Management | D17: 6 | E17: =_xlfn.LET(_xlpm.na,COUNTIF('Question Set'!$G$77:$G$82,"Not Applicable"),IF(_xlpm.na=0,"-",_xlpm.na)) -> - | F17: =_xlfn.LET(_xlpm.u,COUNTIF('Question Set'!$G$77:$G$82,"Unknown"),IF(_xlpm.u=0,"-",_xlpm.u)) -> - | G17: =_xlfn.LET(_xlpm.n,COUNTIF('Question Set'!$G$77:$G$82,"No"),IF(_xlpm.n=0,"-",_xlpm.n)) -> 1 | H17: =_xlfn.LET(_xlpm.pl,COUNTIF('Question Set'!$G$77:$G$82,"Planned"),IF(_xlpm.pl=0,"-",_xlpm.pl)) -> 2 | I17: =_xlfn.LET(_xlpm.ip,COUNTIF('Question Set'!$G$77:$G$82,"In Progress"),IF(_xlpm.ip=0,"-",_xlpm.ip)) -> 3 | J17: =_xlfn.LET(_xlpm.y,COUNTIF('Question Set'!$G$77:$G$82,"Yes"),IF(_xlpm.y=0,"-",_xlpm.y)) -> - | K17: =N(H17)+(N(I17)*2)+(N(J17)*3) -> 8 | L17: of | M17: =(SUM(F17:J17)*3) -> 18
C18: Data Access Monitoring & Disclosure Management | D18: 3 | E18: =_xlfn.LET(_xlpm.na,COUNTIF('Question Set'!$G$85:$G$87,"Not Applicable"),IF(_xlpm.na=0,"-",_xlpm.na)) -> - | F18: =_xlfn.LET(_xlpm.u,COUNTIF('Question Set'!$G$85:$G$87,"Unknown"),IF(_xlpm.u=0,"-",_xlpm.u)) -> - | G18: =_xlfn.LET(_xlpm.n,COUNTIF('Question Set'!$G$85:$G$87,"No"),IF(_xlpm.n=0,"-",_xlpm.n)) -> - | H18: =_xlfn.LET(_xlpm.pl,COUNTIF('Question Set'!$G$85:$G$87,"Planned"),IF(_xlpm.pl=0,"-",_xlpm.pl)) -> - | I18: =_xlfn.LET(_xlpm.ip,COUNTIF('Question Set'!$G$85:$G$87,"In Progress"),IF(_xlpm.ip=0,"-",_xlpm.ip)) -> 2 | J18: =_xlfn.LET(_xlpm.y,COUNTIF('Question Set'!$G$85:$G$87,"Yes"),IF(_xlpm.y=0,"-",_xlpm.y)) -> 1 | K18: =N(H18)+(N(I18)*2)+(N(J18)*3) -> 7 | L18: of | M18: =(SUM(F18:J18)*3) -> 9
C19: Domain Total | D19: =SUM(D16:D18) -> 12 | E19: =_xlfn.LET(_xlpm.x,(SUM(E16:E18)),IF(_xlpm.x=0,"-",_xlpm.x)) -> - | F19: =_xlfn.LET(_xlpm.x,(SUM(F16:F18)),IF(_xlpm.x=0,"-",_xlpm.x)) -> - | G19: =_xlfn.LET(_xlpm.x,(SUM(G16:G18)),IF(_xlpm.x=0,"-",_xlpm.x)) -> 3 | H19: =_xlfn.LET(_xlpm.x,(SUM(H16:H18)),IF(_xlpm.x=0,"-",_xlpm.x)) -> 2 | I19: =_xlfn.LET(_xlpm.x,(SUM(I16:I18)),IF(_xlpm.x=0,"-",_xlpm.x)) -> 5 | J19: =_xlfn.LET(_xlpm.x,(SUM(J16:J18)),IF(_xlpm.x=0,"-",_xlpm.x)) -> 2 | K19: =N(H19)+(N(I19)*2)+(N(J19)*3) -> 18 | L19: of | M19: =(SUM(F19:J19)*3) -> 36
B20: Network & Communications Governance | C20: Network Infrastructure & Boundary Controls | D20: 5 | E20: =_xlfn.LET(_xlpm.na,COUNTIF('Question Set'!$G$91:$G$95,"Not Applicable"),IF(_xlpm.na=0,"-",_xlpm.na)) -> - | F20: =_xlfn.LET(_xlpm.u,COUNTIF('Question Set'!$G$91:$G$95,"Unknown"),IF(_xlpm.u=0,"-",_xlpm.u)) -> - | G20: =_xlfn.LET(_xlpm.n,COUNTIF('Question Set'!$G$91:$G$95,"No"),IF(_xlpm.n=0,"-",_xlpm.n)) -> - | H20: =_xlfn.LET(_xlpm.pl,COUNTIF('Question Set'!$G$91:$G$95,"Planned"),IF(_xlpm.pl=0,"-",_xlpm.pl)) -> - | I20: =_xlfn.LET(_xlpm.ip,COUNTIF('Question Set'!$G$91:$G$95,"In Progress"),IF(_xlpm.ip=0,"-",_xlpm.ip)) -> 4 | J20: =_xlfn.LET(_xlpm.y,COUNTIF('Question Set'!$G$91:$G$95,"Yes"),IF(_xlpm.y=0,"-",_xlpm.y)) -> 1 | K20: =N(H20)+(N(I20)*2)+(N(J20)*3) -> 11 | L20: of | M20: =(SUM(F20:J20)*3) -> 15
C21: Network Traffic & Threat Controls | D21: 5 | E21: =_xlfn.LET(_xlpm.na,COUNTIF('Question Set'!$G$98:$G$102,"Not Applicable"),IF(_xlpm.na=0,"-",_xlpm.na)) -> - | F21: =_xlfn.LET(_xlpm.u,COUNTIF('Question Set'!$G$98:$G$102,"Unknown"),IF(_xlpm.u=0,"-",_xlpm.u)) -> - | G21: =_xlfn.LET(_xlpm.n,COUNTIF('Question Set'!$G$98:$G$102,"No"),IF(_xlpm.n=0,"-",_xlpm.n)) -> 1 | H21: =_xlfn.LET(_xlpm.pl,COUNTIF('Question Set'!$G$98:$G$102,"Planned"),IF(_xlpm.pl=0,"-",_xlpm.pl)) -> 2 | I21: =_xlfn.LET(_xlpm.ip,COUNTIF('Question Set'!$G$98:$G$102,"In Progress"),IF(_xlpm.ip=0,"-",_xlpm.ip)) -> 2 | J21: =_xlfn.LET(_xlpm.y,COUNTIF('Question Set'!$G$98:$G$102,"Yes"),IF(_xlpm.y=0,"-",_xlpm.y)) -> - | K21: =N(H21)+(N(I21)*2)+(N(J21)*3) -> 6 | L21: of | M21: =(SUM(F21:J21)*3) -> 15
C22: DNS Governance & Security Controls | D22: 6 | E22: =_xlfn.LET(_xlpm.na,COUNTIF('Question Set'!$G$105:$G$110,"Not Applicable"),IF(_xlpm.na=0,"-",_xlpm.na)) -> - | F22: =_xlfn.LET(_xlpm.u,COUNTIF('Question Set'!$G$105:$G$110,"Unknown"),IF(_xlpm.u=0,"-",_xlpm.u)) -> 1 | G22: =_xlfn.LET(_xlpm.n,COUNTIF('Question Set'!$G$105:$G$110,"No"),IF(_xlpm.n=0,"-",_xlpm.n)) -> 4 | H22: =_xlfn.LET(_xlpm.pl,COUNTIF('Question Set'!$G$105:$G$110,"Planned"),IF(_xlpm.pl=0,"-",_xlpm.pl)) -> - | I22: =_xlfn.LET(_xlpm.ip,COUNTIF('Question Set'!$G$105:$G$110,"In Progress"),IF(_xlpm.ip=0,"-",_xlpm.ip)) -> 1 | J22: =_xlfn.LET(_xlpm.y,COUNTIF('Question Set'!$G$105:$G$110,"Yes"),IF(_xlpm.y=0,"-",_xlpm.y)) -> - | K22: =N(H22)+(N(I22)*2)+(N(J22)*3) -> 2 | L22: of | M22: =(SUM(F22:J22)*3) -> 18
C23: Email System Security & Threat Protection | D23: 4 | E23: =_xlfn.LET(_xlpm.na,COUNTIF('Question Set'!$G$113:$G$116,"Not Applicable"),IF(_xlpm.na=0,"-",_xlpm.na)) -> 1 | F23: =_xlfn.LET(_xlpm.u,COUNTIF('Question Set'!$G$113:$G$116,"Unknown"),IF(_xlpm.u=0,"-",_xlpm.u)) -> - | G23: =_xlfn.LET(_xlpm.n,COUNTIF('Question Set'!$G$113:$G$116,"No"),IF(_xlpm.n=0,"-",_xlpm.n)) -> - | H23: =_xlfn.LET(_xlpm.pl,COUNTIF('Question Set'!$G$113:$G$116,"Planned"),IF(_xlpm.pl=0,"-",_xlpm.pl)) -> - | I23: =_xlfn.LET(_xlpm.ip,COUNTIF('Question Set'!$G$113:$G$116,"In Progress"),IF(_xlpm.ip=0,"-",_xlpm.ip)) -> - | J23: =_xlfn.LET(_xlpm.y,COUNTIF('Question Set'!$G$113:$G$116,"Yes"),IF(_xlpm.y=0,"-",_xlpm.y)) -> 3 | K23: =N(H23)+(N(I23)*2)+(N(J23)*3) -> 9 | L23: of | M23: =(SUM(F23:J23)*3) -> 9
C24: Wireless & Cellular Communications Security | D24: 5 | E24: =_xlfn.LET(_xlpm.na,COUNTIF('Question Set'!$G$119:$G$123,"Not Applicable"),IF(_xlpm.na=0,"-",_xlpm.na)) -> 1 | F24: =_xlfn.LET(_xlpm.u,COUNTIF('Question Set'!$G$119:$G$123,"Unknown"),IF(_xlpm.u=0,"-",_xlpm.u)) -> 1 | G24: =_xlfn.LET(_xlpm.n,COUNTIF('Question Set'!$G$119:$G$123,"No"),IF(_xlpm.n=0,"-",_xlpm.n)) -> 1 | H24: =_xlfn.LET(_xlpm.pl,COUNTIF('Question Set'!$G$119:$G$123,"Planned"),IF(_xlpm.pl=0,"-",_xlpm.pl)) -> 1 | I24: =_xlfn.LET(_xlpm.ip,COUNTIF('Question Set'!$G$119:$G$123,"In Progress"),IF(_xlpm.ip=0,"-",_xlpm.ip)) -> 1 | J24: =_xlfn.LET(_xlpm.y,COUNTIF('Question Set'!$G$119:$G$123,"Yes"),IF(_xlpm.y=0,"-",_xlpm.y)) -> - | K24: =N(H24)+(N(I24)*2)+(N(J24)*3) -> 3 | L24: of | M24: =(SUM(F24:J24)*3) -> 12
C25: Device & Remote Connectivity Controls | D25: 4 | E25: =_xlfn.LET(_xlpm.na,COUNTIF('Question Set'!$G$126:$G$129,"Not Applicable"),IF(_xlpm.na=0,"-",_xlpm.na)) -> - | F25: =_xlfn.LET(_xlpm.u,COUNTIF('Question Set'!$G$126:$G$129,"Unknown"),IF(_xlpm.u=0,"-",_xlpm.u)) -> 1 | G25: =_xlfn.LET(_xlpm.n,COUNTIF('Question Set'!$G$126:$G$129,"No"),IF(_xlpm.n=0,"-",_xlpm.n)) -> 2 | H25: =_xlfn.LET(_xlpm.pl,COUNTIF('Question Set'!$G$126:$G$129,"Planned"),IF(_xlpm.pl=0,"-",_xlpm.pl)) -> - | I25: =_xlfn.LET(_xlpm.ip,COUNTIF('Question Set'!$G$126:$G$129,"In Progress"),IF(_xlpm.ip=0,"-",_xlpm.ip)) -> 1 | J25: =_xlfn.LET(_xlpm.y,COUNTIF('Question Set'!$G$126:$G$129,"Yes"),IF(_xlpm.y=0,"-",_xlpm.y)) -> - | K25: =N(H25)+(N(I25)*2)+(N(J25)*3) -> 2 | L25: of | M25: =(SUM(F25:J25)*3) -> 12
C26: Domain Total | D26: =SUM(D20:D25) -> 29 | E26: =_xlfn.LET(_xlpm.x,SUM(E20:E25),IF(_xlpm.x=0,"-",_xlpm.x)) -> 2 | F26: =_xlfn.LET(_xlpm.x,SUM(F20:F25),IF(_xlpm.x=0,"-",_xlpm.x)) -> 3 | G26: =_xlfn.LET(_xlpm.x,SUM(G20:G25),IF(_xlpm.x=0,"-",_xlpm.x)) -> 8 | H26: =_xlfn.LET(_xlpm.x,SUM(H20:H25),IF(_xlpm.x=0,"-",_xlpm.x)) -> 3 | I26: =_xlfn.LET(_xlpm.x,SUM(I20:I25),IF(_xlpm.x=0,"-",_xlpm.x)) -> 9 | J26: =_xlfn.LET(_xlpm.x,SUM(J20:J25),IF(_xlpm.x=0,"-",_xlpm.x)) -> 4 | K26: =N(H26)+(N(I26)*2)+(N(J26)*3) -> 33 | L26: of | M26: =(SUM(F26:J26)*3) -> 81
B27: Endpoint Security & Configuration Management | C27: Baseline Configuration & Asset Management | D27: 5 | E27: =_xlfn.LET(_xlpm.na,COUNTIF('Question Set'!$G$133:$G$137,"Not Applicable"),IF(_xlpm.na=0,"-",_xlpm.na)) -> - | F27: =_xlfn.LET(_xlpm.u,COUNTIF('Question Set'!$G$133:$G$137,"Unknown"),IF(_xlpm.u=0,"-",_xlpm.u)) -> - | G27: =_xlfn.LET(_xlpm.n,COUNTIF('Question Set'!$G$133:$G$137,"No"),IF(_xlpm.n=0,"-",_xlpm.n)) -> 2 | H27: =_xlfn.LET(_xlpm.pl,COUNTIF('Question Set'!$G$133:$G$137,"Planned"),IF(_xlpm.pl=0,"-",_xlpm.pl)) -> 1 | I27: =_xlfn.LET(_xlpm.ip,COUNTIF('Question Set'!$G$133:$G$137,"In Progress"),IF(_xlpm.ip=0,"-",_xlpm.ip)) -> 1 | J27: =_xlfn.LET(_xlpm.y,COUNTIF('Question Set'!$G$133:$G$137,"Yes"),IF(_xlpm.y=0,"-",_xlpm.y)) -> 1 | K27: =N(H27)+(N(I27)*2)+(N(J27)*3) -> 6 | L27: of | M27: =(SUM(F27:J27)*3) -> 15
C28: Service & Endpoint Hardening Controls | D28: 5 | E28: =_xlfn.LET(_xlpm.na,COUNTIF('Question Set'!$G$140:$G$144,"Not Applicable"),IF(_xlpm.na=0,"-",_xlpm.na)) -> 1 | F28: =_xlfn.LET(_xlpm.u,COUNTIF('Question Set'!$G$140:$G$144,"Unknown"),IF(_xlpm.u=0,"-",_xlpm.u)) -> - | G28: =_xlfn.LET(_xlpm.n,COUNTIF('Question Set'!$G$140:$G$144,"No"),IF(_xlpm.n=0,"-",_xlpm.n)) -> 2 | H28: =_xlfn.LET(_xlpm.pl,COUNTIF('Question Set'!$G$140:$G$144,"Planned"),IF(_xlpm.pl=0,"-",_xlpm.pl)) -> - | I28: =_xlfn.LET(_xlpm.ip,COUNTIF('Question Set'!$G$140:$G$144,"In Progress"),IF(_xlpm.ip=0,"-",_xlpm.ip)) -> - | J28: =_xlfn.LET(_xlpm.y,COUNTIF('Question Set'!$G$140:$G$144,"Yes"),IF(_xlpm.y=0,"-",_xlpm.y)) -> 2 | K28: =N(H28)+(N(I28)*2)+(N(J28)*3) -> 6 | L28: of | M28: =(SUM(F28:J28)*3) -> 12
C29: Configuration, Change & Patch Management | D29: 5 | E29: =_xlfn.LET(_xlpm.na,COUNTIF('Question Set'!$G$147:$G$151,"Not Applicable"),IF(_xlpm.na=0,"-",_xlpm.na)) -> 2 | F29: =_xlfn.LET(_xlpm.u,COUNTIF('Question Set'!$G$147:$G$151,"Unknown"),IF(_xlpm.u=0,"-",_xlpm.u)) -> - | G29: =_xlfn.LET(_xlpm.n,COUNTIF('Question Set'!$G$147:$G$151,"No"),IF(_xlpm.n=0,"-",_xlpm.n)) -> 2 | H29: =_xlfn.LET(_xlpm.pl,COUNTIF('Question Set'!$G$147:$G$151,"Planned"),IF(_xlpm.pl=0,"-",_xlpm.pl)) -> - | I29: =_xlfn.LET(_xlpm.ip,COUNTIF('Question Set'!$G$147:$G$151,"In Progress"),IF(_xlpm.ip=0,"-",_xlpm.ip)) -> - | J29: =_xlfn.LET(_xlpm.y,COUNTIF('Question Set'!$G$147:$G$151,"Yes"),IF(_xlpm.y=0,"-",_xlpm.y)) -> 1 | K29: =N(H29)+(N(I29)*2)+(N(J29)*3) -> 3 | L29: of | M29: =(SUM(F29:J29)*3) -> 9
C30: Endpoint & Remote Device Security | D30: 4 | E30: =_xlfn.LET(_xlpm.na,COUNTIF('Question Set'!$G$154:$G$157,"Not Applicable"),IF(_xlpm.na=0,"-",_xlpm.na)) -> - | F30: =_xlfn.LET(_xlpm.u,COUNTIF('Question Set'!$G$154:$G$157,"Unknown"),IF(_xlpm.u=0,"-",_xlpm.u)) -> - | G30: =_xlfn.LET(_xlpm.n,COUNTIF('Question Set'!$G$154:$G$157,"No"),IF(_xlpm.n=0,"-",_xlpm.n)) -> 2 | H30: =_xlfn.LET(_xlpm.pl,COUNTIF('Question Set'!$G$154:$G$157,"Planned"),IF(_xlpm.pl=0,"-",_xlpm.pl)) -> - | I30: =_xlfn.LET(_xlpm.ip,COUNTIF('Question Set'!$G$154:$G$157,"In Progress"),IF(_xlpm.ip=0,"-",_xlpm.ip)) -> - | J30: =_xlfn.LET(_xlpm.y,COUNTIF('Question Set'!$G$154:$G$157,"Yes"),IF(_xlpm.y=0,"-",_xlpm.y)) -> 2 | K30: =N(H30)+(N(I30)*2)+(N(J30)*3) -> 6 | L30: of | M30: =(SUM(F30:J30)*3) -> 12
C31: Domain Total | D31: =SUM(D27:D30) -> 19 | E31: =_xlfn.LET(_xlpm.x,SUM(E27:E30),IF(_xlpm.x=0,"-",_xlpm.x)) -> 3 | F31: =_xlfn.LET(_xlpm.x,SUM(F27:F30),IF(_xlpm.x=0,"-",_xlpm.x)) -> - | G31: =_xlfn.LET(_xlpm.x,SUM(G27:G30),IF(_xlpm.x=0,"-",_xlpm.x)) -> 8 | H31: =_xlfn.LET(_xlpm.x,SUM(H27:H30),IF(_xlpm.x=0,"-",_xlpm.x)) -> 1 | I31: =_xlfn.LET(_xlpm.x,SUM(I27:I30),IF(_xlpm.x=0,"-",_xlpm.x)) -> 1 | J31: =_xlfn.LET(_xlpm.x,SUM(J27:J30),IF(_xlpm.x=0,"-",_xlpm.x)) -> 6 | K31: =N(H31)+(N(I31)*2)+(N(J31)*3) -> 21 | L31: of | M31: =(SUM(F31:J31)*3) -> 48
B32: Cryptography, Encryption & Key Management Governance | C32: Encryption & Cryptography Governance | D32: 3 | E32: =_xlfn.LET(_xlpm.na,COUNTIF('Question Set'!$G$161:$G$163,"Not Applicable"),IF(_xlpm.na=0,"-",_xlpm.na)) -> - | F32: =_xlfn.LET(_xlpm.u,COUNTIF('Question Set'!$G$161:$G$163,"Unknown"),IF(_xlpm.u=0,"-",_xlpm.u)) -> 1 | G32: =_xlfn.LET(_xlpm.n,COUNTIF('Question Set'!$G$161:$G$163,"No"),IF(_xlpm.n=0,"-",_xlpm.n)) -> 2 | H32: =_xlfn.LET(_xlpm.pl,COUNTIF('Question Set'!$G$161:$G$163,"Planned"),IF(_xlpm.pl=0,"-",_xlpm.pl)) -> - | I32: =_xlfn.LET(_xlpm.ip,COUNTIF('Question Set'!$G$161:$G$163,"In Progress"),IF(_xlpm.ip=0,"-",_xlpm.ip)) -> - | J32: =_xlfn.LET(_xlpm.y,COUNTIF('Question Set'!$G$161:$G$163,"Yes"),IF(_xlpm.y=0,"-",_xlpm.y)) -> - | K32: =N(H32)+(N(I32)*2)+(N(J32)*3) -> 0 | L32: of | M32: =(SUM(F32:J32)*3) -> 9
C33: PKI & Certificate Management | D33: 3 | E33: =_xlfn.LET(_xlpm.na,COUNTIF('Question Set'!$G$166:$G$168,"Not Applicable"),IF(_xlpm.na=0,"-",_xlpm.na)) -> - | F33: =_xlfn.LET(_xlpm.u,COUNTIF('Question Set'!$G$166:$G$168,"Unknown"),IF(_xlpm.u=0,"-",_xlpm.u)) -> - | G33: =_xlfn.LET(_xlpm.n,COUNTIF('Question Set'!$G$166:$G$168,"No"),IF(_xlpm.n=0,"-",_xlpm.n)) -> 3 | H33: =_xlfn.LET(_xlpm.pl,COUNTIF('Question Set'!$G$166:$G$168,"Planned"),IF(_xlpm.pl=0,"-",_xlpm.pl)) -> - | I33: =_xlfn.LET(_xlpm.ip,COUNTIF('Question Set'!$G$166:$G$168,"In Progress"),IF(_xlpm.ip=0,"-",_xlpm.ip)) -> - | J33: =_xlfn.LET(_xlpm.y,COUNTIF('Question Set'!$G$166:$G$168,"Yes"),IF(_xlpm.y=0,"-",_xlpm.y)) -> - | K33: =N(H33)+(N(I33)*2)+(N(J33)*3) -> 0 | L33: of | M33: =(SUM(F33:J33)*3) -> 9
C34: Cryptographic Key Governance & Availability | D34: 4 | E34: =_xlfn.LET(_xlpm.na,COUNTIF('Question Set'!$G$171:$G$174,"Not Applicable"),IF(_xlpm.na=0,"-",_xlpm.na)) -> 1 | F34: =_xlfn.LET(_xlpm.u,COUNTIF('Question Set'!$G$171:$G$174,"Unknown"),IF(_xlpm.u=0,"-",_xlpm.u)) -> - | G34: =_xlfn.LET(_xlpm.n,COUNTIF('Question Set'!$G$171:$G$174,"No"),IF(_xlpm.n=0,"-",_xlpm.n)) -> 3 | H34: =_xlfn.LET(_xlpm.pl,COUNTIF('Question Set'!$G$171:$G$174,"Planned"),IF(_xlpm.pl=0,"-",_xlpm.pl)) -> - | I34: =_xlfn.LET(_xlpm.ip,COUNTIF('Question Set'!$G$171:$G$174,"In Progress"),IF(_xlpm.ip=0,"-",_xlpm.ip)) -> - | J34: =_xlfn.LET(_xlpm.y,COUNTIF('Question Set'!$G$171:$G$174,"Yes"),IF(_xlpm.y=0,"-",_xlpm.y)) -> - | K34: =N(H34)+(N(I34)*2)+(N(J34)*3) -> 0 | L34: of | M34: =(SUM(F34:J34)*3) -> 9
C35: Domain Total | D35: =SUM(D32:D34) -> 10 | E35: =_xlfn.LET(_xlpm.x,SUM(E32:E34),IF(_xlpm.x=0,"-",_xlpm.x)) -> 1 | F35: =_xlfn.LET(_xlpm.x,SUM(F32:F34),IF(_xlpm.x=0,"-",_xlpm.x)) -> 1 | G35: =_xlfn.LET(_xlpm.x,SUM(G32:G34),IF(_xlpm.x=0,"-",_xlpm.x)) -> 8 | H35: =_xlfn.LET(_xlpm.x,SUM(H32:H34),IF(_xlpm.x=0,"-",_xlpm.x)) -> - | I35: =_xlfn.LET(_xlpm.x,SUM(I32:I34),IF(_xlpm.x=0,"-",_xlpm.x)) -> - | J35: =_xlfn.LET(_xlpm.x,SUM(J32:J34),IF(_xlpm.x=0,"-",_xlpm.x)) -> - | K35: =N(H35)+(N(I35)*2)+(N(J35)*3) -> 0 | L35: of | M35: =(SUM(F35:J35)*3) -> 27
B36: Logging, Monitoring & Event Detection | C36: Logging Policy, Content & Review | D36: 4 | E36: =_xlfn.LET(_xlpm.na,COUNTIF('Question Set'!$G$178:$G$181,"Not Applicable"),IF(_xlpm.na=0,"-",_xlpm.na)) -> - | F36: =_xlfn.LET(_xlpm.u,COUNTIF('Question Set'!$G$178:$G$181,"Unknown"),IF(_xlpm.u=0,"-",_xlpm.u)) -> - | G36: =_xlfn.LET(_xlpm.n,COUNTIF('Question Set'!$G$178:$G$181,"No"),IF(_xlpm.n=0,"-",_xlpm.n)) -> 2 | H36: =_xlfn.LET(_xlpm.pl,COUNTIF('Question Set'!$G$178:$G$181,"Planned"),IF(_xlpm.pl=0,"-",_xlpm.pl)) -> - | I36: =_xlfn.LET(_xlpm.ip,COUNTIF('Question Set'!$G$178:$G$181,"In Progress"),IF(_xlpm.ip=0,"-",_xlpm.ip)) -> 2 | J36: =_xlfn.LET(_xlpm.y,COUNTIF('Question Set'!$G$178:$G$181,"Yes"),IF(_xlpm.y=0,"-",_xlpm.y)) -> - | K36: =N(H36)+(N(I36)*2)+(N(J36)*3) -> 4 | L36: of | M36: =(SUM(F36:J36)*3) -> 12
C37: Continuous Monitoring & Threat Detection | D37: 5 | E37: =_xlfn.LET(_xlpm.na,COUNTIF('Question Set'!$G$184:$G$188,"Not Applicable"),IF(_xlpm.na=0,"-",_xlpm.na)) -> - | F37: =_xlfn.LET(_xlpm.u,COUNTIF('Question Set'!$G$184:$G$188,"Unknown"),IF(_xlpm.u=0,"-",_xlpm.u)) -> - | G37: =_xlfn.LET(_xlpm.n,COUNTIF('Question Set'!$G$184:$G$188,"No"),IF(_xlpm.n=0,"-",_xlpm.n)) -> 3 | H37: =_xlfn.LET(_xlpm.pl,COUNTIF('Question Set'!$G$184:$G$188,"Planned"),IF(_xlpm.pl=0,"-",_xlpm.pl)) -> - | I37: =_xlfn.LET(_xlpm.ip,COUNTIF('Question Set'!$G$184:$G$188,"In Progress"),IF(_xlpm.ip=0,"-",_xlpm.ip)) -> 2 | J37: =_xlfn.LET(_xlpm.y,COUNTIF('Question Set'!$G$184:$G$188,"Yes"),IF(_xlpm.y=0,"-",_xlpm.y)) -> - | K37: =N(H37)+(N(I37)*2)+(N(J37)*3) -> 4 | L37: of | M37: =(SUM(F37:J37)*3) -> 15
C38: Security Event Review & Detection | D38: 4 | E38: =_xlfn.LET(_xlpm.na,COUNTIF('Question Set'!$G$191:$G$194,"Not Applicable"),IF(_xlpm.na=0,"-",_xlpm.na)) -> - | F38: =_xlfn.LET(_xlpm.u,COUNTIF('Question Set'!$G$191:$G$194,"Unknown"),IF(_xlpm.u=0,"-",_xlpm.u)) -> - | G38: =_xlfn.LET(_xlpm.n,COUNTIF('Question Set'!$G$191:$G$194,"No"),IF(_xlpm.n=0,"-",_xlpm.n)) -> 3 | H38: =_xlfn.LET(_xlpm.pl,COUNTIF('Question Set'!$G$191:$G$194,"Planned"),IF(_xlpm.pl=0,"-",_xlpm.pl)) -> - | I38: =_xlfn.LET(_xlpm.ip,COUNTIF('Question Set'!$G$191:$G$194,"In Progress"),IF(_xlpm.ip=0,"-",_xlpm.ip)) -> 1 | J38: =_xlfn.LET(_xlpm.y,COUNTIF('Question Set'!$G$191:$G$194,"Yes"),IF(_xlpm.y=0,"-",_xlpm.y)) -> - | K38: =N(H38)+(N(I38)*2)+(N(J38)*3) -> 2 | L38: of | M38: =(SUM(F38:J38)*3) -> 12
C39: Time Synchronization & Log Integrity | D39: 2 | E39: =_xlfn.LET(_xlpm.na,COUNTIF('Question Set'!$G$197:$G$198,"Not Applicable"),IF(_xlpm.na=0,"-",_xlpm.na)) -> - | F39: =_xlfn.LET(_xlpm.u,COUNTIF('Question Set'!$G$197:$G$198,"Unknown"),IF(_xlpm.u=0,"-",_xlpm.u)) -> - | G39: =_xlfn.LET(_xlpm.n,COUNTIF('Question Set'!$G$197:$G$198,"No"),IF(_xlpm.n=0,"-",_xlpm.n)) -> 1 | H39: =_xlfn.LET(_xlpm.pl,COUNTIF('Question Set'!$G$197:$G$198,"Planned"),IF(_xlpm.pl=0,"-",_xlpm.pl)) -> - | I39: =_xlfn.LET(_xlpm.ip,COUNTIF('Question Set'!$G$197:$G$198,"In Progress"),IF(_xlpm.ip=0,"-",_xlpm.ip)) -> 1 | J39: =_xlfn.LET(_xlpm.y,COUNTIF('Question Set'!$G$197:$G$198,"Yes"),IF(_xlpm.y=0,"-",_xlpm.y)) -> - | K39: =N(H39)+(N(I39)*2)+(N(J39)*3) -> 2 | L39: of | M39: =(SUM(F39:J39)*3) -> 6
C40: Domain Total | D40: =SUM(D36:D39) -> 15 | E40: =_xlfn.LET(_xlpm.x,SUM(E36:E39),IF(_xlpm.x=0,"-",_xlpm.x)) -> - | F40: =_xlfn.LET(_xlpm.x,SUM(F36:F39),IF(_xlpm.x=0,"-",_xlpm.x)) -> - | G40: =_xlfn.LET(_xlpm.x,SUM(G36:G39),IF(_xlpm.x=0,"-",_xlpm.x)) -> 9 | H40: =_xlfn.LET(_xlpm.x,SUM(H36:H39),IF(_xlpm.x=0,"-",_xlpm.x)) -> - | I40: =_xlfn.LET(_xlpm.x,SUM(I36:I39),IF(_xlpm.x=0,"-",_xlpm.x)) -> 6 | J40: =_xlfn.LET(_xlpm.x,SUM(J36:J39),IF(_xlpm.x=0,"-",_xlpm.x)) -> - | K40: =N(H40)+(N(I40)*2)+(N(J40)*3) -> 12 | L40: of | M40: =(SUM(F40:J40)*3) -> 45
B41: Response, Recovery & Forensic Readiness | C41: Incident Response Planning & Procedures | D41: 2 | E41: =_xlfn.LET(_xlpm.na,COUNTIF('Question Set'!$G$202:$G$203,"Not Applicable"),IF(_xlpm.na=0,"-",_xlpm.na)) -> - | F41: =_xlfn.LET(_xlpm.u,COUNTIF('Question Set'!$G$202:$G$203,"Unknown"),IF(_xlpm.u=0,"-",_xlpm.u)) -> - | G41: =_xlfn.LET(_xlpm.n,COUNTIF('Question Set'!$G$202:$G$203,"No"),IF(_xlpm.n=0,"-",_xlpm.n)) -> - | H41: =_xlfn.LET(_xlpm.pl,COUNTIF('Question Set'!$G$202:$G$203,"Planned"),IF(_xlpm.pl=0,"-",_xlpm.pl)) -> 1 | I41: =_xlfn.LET(_xlpm.ip,COUNTIF('Question Set'!$G$202:$G$203,"In Progress"),IF(_xlpm.ip=0,"-",_xlpm.ip)) -> 1 | J41: =_xlfn.LET(_xlpm.y,COUNTIF('Question Set'!$G$202:$G$203,"Yes"),IF(_xlpm.y=0,"-",_xlpm.y)) -> - | K41: =N(H41)+(N(I41)*2)+(N(J41)*3) -> 3 | L41: of | M41: =(SUM(F41:J41)*3) -> 6
C42: Incident Response Execution & Resilience | D42: 4 | E42: =_xlfn.LET(_xlpm.na,COUNTIF('Question Set'!$G$206:$G$209,"Not Applicable"),IF(_xlpm.na=0,"-",_xlpm.na)) -> - | F42: =_xlfn.LET(_xlpm.u,COUNTIF('Question Set'!$G$206:$G$209,"Unknown"),IF(_xlpm.u=0,"-",_xlpm.u)) -> - | G42: =_xlfn.LET(_xlpm.n,COUNTIF('Question Set'!$G$206:$G$209,"No"),IF(_xlpm.n=0,"-",_xlpm.n)) -> - | H42: =_xlfn.LET(_xlpm.pl,COUNTIF('Question Set'!$G$206:$G$209,"Planned"),IF(_xlpm.pl=0,"-",_xlpm.pl)) -> 1 | I42: =_xlfn.LET(_xlpm.ip,COUNTIF('Question Set'!$G$206:$G$209,"In Progress"),IF(_xlpm.ip=0,"-",_xlpm.ip)) -> 3 | J42: =_xlfn.LET(_xlpm.y,COUNTIF('Question Set'!$G$206:$G$209,"Yes"),IF(_xlpm.y=0,"-",_xlpm.y)) -> - | K42: =N(H42)+(N(I42)*2)+(N(J42)*3) -> 7 | L42: of | M42: =(SUM(F42:J42)*3) -> 12
C43: Forensic Readiness & Evidence Management | D43: 4 | E43: =_xlfn.LET(_xlpm.na,COUNTIF('Question Set'!$G$212:$G$215,"Not Applicable"),IF(_xlpm.na=0,"-",_xlpm.na)) -> - | F43: =_xlfn.LET(_xlpm.u,COUNTIF('Question Set'!$G$212:$G$215,"Unknown"),IF(_xlpm.u=0,"-",_xlpm.u)) -> - | G43: =_xlfn.LET(_xlpm.n,COUNTIF('Question Set'!$G$212:$G$215,"No"),IF(_xlpm.n=0,"-",_xlpm.n)) -> 2 | H43: =_xlfn.LET(_xlpm.pl,COUNTIF('Question Set'!$G$212:$G$215,"Planned"),IF(_xlpm.pl=0,"-",_xlpm.pl)) -> - | I43: =_xlfn.LET(_xlpm.ip,COUNTIF('Question Set'!$G$212:$G$215,"In Progress"),IF(_xlpm.ip=0,"-",_xlpm.ip)) -> - | J43: =_xlfn.LET(_xlpm.y,COUNTIF('Question Set'!$G$212:$G$215,"Yes"),IF(_xlpm.y=0,"-",_xlpm.y)) -> 2 | K43: =N(H43)+(N(I43)*2)+(N(J43)*3) -> 6 | L43: of | M43: =(SUM(F43:J43)*3) -> 12
C44: Domain Total | D44: =SUM(D41:D43) -> 10 | E44: =_xlfn.LET(_xlpm.x,SUM(E41:E43),IF(_xlpm.x=0,"-",_xlpm.x)) -> - | F44: =_xlfn.LET(_xlpm.x,SUM(F41:F43),IF(_xlpm.x=0,"-",_xlpm.x)) -> - | G44: =_xlfn.LET(_xlpm.x,SUM(G41:G43),IF(_xlpm.x=0,"-",_xlpm.x)) -> 2 | H44: =_xlfn.LET(_xlpm.x,SUM(H41:H43),IF(_xlpm.x=0,"-",_xlpm.x)) -> 2 | I44: =_xlfn.LET(_xlpm.x,SUM(I41:I43),IF(_xlpm.x=0,"-",_xlpm.x)) -> 4 | J44: =_xlfn.LET(_xlpm.x,SUM(J41:J43),IF(_xlpm.x=0,"-",_xlpm.x)) -> 2 | K44: =N(H44)+(N(I44)*2)+(N(J44)*3) -> 16 | L44: of | M44: =(SUM(F44:J44)*3) -> 30
B45: Business Continuity & Environmental Resilience | C45: Continuity Planning & Recovery | D45: 4 | E45: =_xlfn.LET(_xlpm.na,COUNTIF('Question Set'!$G$219:$G$222,"Not Applicable"),IF(_xlpm.na=0,"-",_xlpm.na)) -> 1 | F45: =_xlfn.LET(_xlpm.u,COUNTIF('Question Set'!$G$219:$G$222,"Unknown"),IF(_xlpm.u=0,"-",_xlpm.u)) -> - | G45: =_xlfn.LET(_xlpm.n,COUNTIF('Question Set'!$G$219:$G$222,"No"),IF(_xlpm.n=0,"-",_xlpm.n)) -> - | H45: =_xlfn.LET(_xlpm.pl,COUNTIF('Question Set'!$G$219:$G$222,"Planned"),IF(_xlpm.pl=0,"-",_xlpm.pl)) -> 1 | I45: =_xlfn.LET(_xlpm.ip,COUNTIF('Question Set'!$G$219:$G$222,"In Progress"),IF(_xlpm.ip=0,"-",_xlpm.ip)) -> 2 | J45: =_xlfn.LET(_xlpm.y,COUNTIF('Question Set'!$G$219:$G$222,"Yes"),IF(_xlpm.y=0,"-",_xlpm.y)) -> - | K45: =N(H45)+(N(I45)*2)+(N(J45)*3) -> 5 | L45: of | M45: =(SUM(F45:J45)*3) -> 9
C46: Backup & Restoration Management | D46: 4 | E46: =_xlfn.LET(_xlpm.na,COUNTIF('Question Set'!$G$225:$G$228,"Not Applicable"),IF(_xlpm.na=0,"-",)) -> - | F46: =_xlfn.LET(_xlpm.u,COUNTIF('Question Set'!$G$225:$G$228,"Unknown"),IF(_xlpm.u=0,"-",_xlpm.u)) -> - | G46: =_xlfn.LET(_xlpm.n,COUNTIF('Question Set'!$G$225:$G$228,"No"),IF(_xlpm.n=0,"-",_xlpm.n)) -> - | H46: =_xlfn.LET(_xlpm.pl,COUNTIF('Question Set'!$G$225:$G$228,"Planned"),IF(_xlpm.pl=0,"-",_xlpm.pl)) -> 1 | I46: =_xlfn.LET(_xlpm.ip,COUNTIF('Question Set'!$G$225:$G$228,"In Progress"),IF(_xlpm.ip=0,"-",_xlpm.ip)) -> 2 | J46: =_xlfn.LET(_xlpm.y,COUNTIF('Question Set'!$G$225:$G$228,"Yes"),IF(_xlpm.y=0,"-",_xlpm.y)) -> 1 | K46: =N(H46)+(N(I46)*2)+(N(J46)*3) -> 8 | L46: of | M46: =(SUM(F46:J46)*3) -> 12
C47: Redundancy, Recovery & Resilience | D47: 4 | E47: =_xlfn.LET(_xlpm.na,COUNTIF('Question Set'!$G$231:$G$234,"Not Applicable"),IF(_xlpm.na=0,"-",_xlpm.na)) -> - | F47: =_xlfn.LET(_xlpm.u,COUNTIF('Question Set'!$G$231:$G$234,"Unknown"),IF(_xlpm.u=0,"-",_xlpm.u)) -> - | G47: =_xlfn.LET(_xlpm.n,COUNTIF('Question Set'!$G$231:$G$234,"No"),IF(_xlpm.n=0,"-",_xlpm.n)) -> - | H47: =_xlfn.LET(_xlpm.pl,COUNTIF('Question Set'!$G$231:$G$234,"Planned"),IF(_xlpm.pl=0,"-",_xlpm.pl)) -> - | I47: =_xlfn.LET(_xlpm.ip,COUNTIF('Question Set'!$G$231:$G$234,"In Progress"),IF(_xlpm.ip=0,"-",_xlpm.ip)) -> 4 | J47: =_xlfn.LET(_xlpm.y,COUNTIF('Question Set'!$G$231:$G$234,"Yes"),IF(_xlpm.y=0,"-",_xlpm.y)) -> - | K47: =N(H47)+(N(I47)*2)+(N(J47)*3) -> 8 | L47: of | M47: =(SUM(F47:J47)*3) -> 12
C48: Power & Environmental Resilience | D48: 3 | E48: =_xlfn.LET(_xlpm.na,COUNTIF('Question Set'!$G$237:$G$239,"Not Applicable"),IF(_xlpm.na=0,"-",_xlpm.na)) -> - | F48: =_xlfn.LET(_xlpm.u,COUNTIF('Question Set'!$G$237:$G$239,"Unknown"),IF(_xlpm.u=0,"-",_xlpm.u)) -> 1 | G48: =_xlfn.LET(_xlpm.n,COUNTIF('Question Set'!$G$237:$G$239,"No"),IF(_xlpm.n=0,"-",_xlpm.n)) -> - | H48: =_xlfn.LET(_xlpm.pl,COUNTIF('Question Set'!$G$237:$G$239,"Planned"),IF(_xlpm.pl=0,"-",_xlpm.pl)) -> - | I48: =_xlfn.LET(_xlpm.ip,COUNTIF('Question Set'!$G$237:$G$239,"In Progress"),IF(_xlpm.ip=0,"-",_xlpm.ip)) -> 2 | J48: =_xlfn.LET(_xlpm.y,COUNTIF('Question Set'!$G$237:$G$239,"Yes"),IF(_xlpm.y=0,"-",_xlpm.y)) -> - | K48: =N(H48)+(N(I48)*2)+(N(J48)*3) -> 4 | L48: of | M48: =(SUM(F48:J48)*3) -> 9
C49: Domain Total | D49: =SUM(D45:D48) -> 15 | E49: =_xlfn.LET(_xlpm.x,SUM(E45:E48),IF(_xlpm.x=0,"-",_xlpm.x)) -> 1 | F49: =_xlfn.LET(_xlpm.x,SUM(F45:F48),IF(_xlpm.x=0,"-",_xlpm.x)) -> 1 | G49: =_xlfn.LET(_xlpm.x,SUM(G45:G48),IF(_xlpm.x=0,"-",_xlpm.x)) -> - | H49: =_xlfn.LET(_xlpm.x,SUM(H45:H48),IF(_xlpm.x=0,"-",_xlpm.x)) -> 2 | I49: =_xlfn.LET(_xlpm.x,SUM(I45:I48),IF(_xlpm.x=0,"-",_xlpm.x)) -> 10 | J49: =_xlfn.LET(_xlpm.x,SUM(J45:J48),IF(_xlpm.x=0,"-",_xlpm.x)) -> 1 | K49: =N(H49)+(N(I49)*2)+(N(J49)*3) -> 25 | L49: of | M49: =(SUM(F49:J49)*3) -> 42
B50: Physical & Environmental Security Management | C50: Facility Access Control & Perimeter Security | D50: 6 | E50: =_xlfn.LET(_xlpm.na,COUNTIF('Question Set'!$G$243:$G$248,"Not Applicable"),IF(_xlpm.na=0,"-",_xlpm.na)) -> - | F50: =_xlfn.LET(_xlpm.u,COUNTIF('Question Set'!$G$243:$G$248,"Unknown"),IF(_xlpm.u=0,"-",_xlpm.u)) -> - | G50: =_xlfn.LET(_xlpm.n,COUNTIF('Question Set'!$G$243:$G$248,"No"),IF(_xlpm.n=0,"-",_xlpm.n)) -> 4 | H50: =_xlfn.LET(_xlpm.pl,COUNTIF('Question Set'!$G$243:$G$248,"Planned"),IF(_xlpm.pl=0,"-",_xlpm.pl)) -> - | I50: =_xlfn.LET(_xlpm.ip,COUNTIF('Question Set'!$G$243:$G$248,"In Progress"),IF(_xlpm.ip=0,"-",_xlpm.ip)) -> - | J50: =_xlfn.LET(_xlpm.y,COUNTIF('Question Set'!$G$243:$G$248,"Yes"),IF(_xlpm.y=0,"-",_xlpm.y)) -> 2 | K50: =N(H50)+(N(I50)*2)+(N(J50)*3) -> 6 | L50: of | M50: =(SUM(F50:J50)*3) -> 18
C51: Visitor Management | D51: 2 | E51: =_xlfn.LET(_xlpm.na,COUNTIF('Question Set'!$G$251:$G$252,"Not Applicable"),IF(_xlpm.na=0,"-",_xlpm.na)) -> - | F51: =_xlfn.LET(_xlpm.u,COUNTIF('Question Set'!$G$251:$G$252,"Unknown"),IF(_xlpm.u=0,"-",_xlpm.u)) -> - | G51: =_xlfn.LET(_xlpm.n,COUNTIF('Question Set'!$G$251:$G$252,"No"),IF(_xlpm.n=0,"-",_xlpm.n)) -> 1 | H51: =_xlfn.LET(_xlpm.pl,COUNTIF('Question Set'!$G$251:$G$252,"Planned"),IF(_xlpm.pl=0,"-",_xlpm.pl)) -> - | I51: =_xlfn.LET(_xlpm.ip,COUNTIF('Question Set'!$G$251:$G$252,"In Progress"),IF(_xlpm.ip=0,"-",_xlpm.ip)) -> 1 | J51: =_xlfn.LET(_xlpm.y,COUNTIF('Question Set'!$G$251:$G$252,"Yes"),IF(_xlpm.y=0,"-",_xlpm.y)) -> - | K51: =N(H51)+(N(I51)*2)+(N(J51)*3) -> 2 | L51: of | M51: =(SUM(F51:J51)*3) -> 6
C52: Physical Access Monitoring & Logging | D52: 3 | E52: =_xlfn.LET(_xlpm.na,COUNTIF('Question Set'!$G$255:$G$257,"Not Applicable"),IF(_xlpm.na=0,"-",_xlpm.na)) -> - | F52: =_xlfn.LET(_xlpm.u,COUNTIF('Question Set'!$G$255:$G$257,"Unknown"),IF(_xlpm.u=0,"-",_xlpm.u)) -> - | G52: =_xlfn.LET(_xlpm.n,COUNTIF('Question Set'!$G$255:$G$257,"No"),IF(_xlpm.n=0,"-",_xlpm.n)) -> 1 | H52: =_xlfn.LET(_xlpm.pl,COUNTIF('Question Set'!$G$255:$G$257,"Planned"),IF(_xlpm.pl=0,"-",_xlpm.pl)) -> - | I52: =_xlfn.LET(_xlpm.ip,COUNTIF('Question Set'!$G$255:$G$257,"In Progress"),IF(_xlpm.ip=0,"-",_xlpm.ip)) -> 1 | J52: =_xlfn.LET(_xlpm.y,COUNTIF('Question Set'!$G$255:$G$257,"Yes"),IF(_xlpm.y=0,"-",_xlpm.y)) -> 1 | K52: =N(H52)+(N(I52)*2)+(N(J52)*3) -> 5 | L52: of | M52: =(SUM(F52:J52)*3) -> 9
C53: Secure Placement & Physical Safeguards | D53: 4 | E53: =_xlfn.LET(_xlpm.na,COUNTIF('Question Set'!$G$260:$G$263,"Not Applicable"),IF(_xlpm.na=0,"-",_xlpm.na)) -> - | F53: =_xlfn.LET(_xlpm.u,COUNTIF('Question Set'!$G$260:$G$263,"Unknown"),IF(_xlpm.u=0,"-",_xlpm.u)) -> - | G53: =_xlfn.LET(_xlpm.n,COUNTIF('Question Set'!$G$260:$G$263,"No"),IF(_xlpm.n=0,"-",_xlpm.n)) -> - | H53: =_xlfn.LET(_xlpm.pl,COUNTIF('Question Set'!$G$260:$G$263,"Planned"),IF(_xlpm.pl=0,"-",_xlpm.pl)) -> - | I53: =_xlfn.LET(_xlpm.ip,COUNTIF('Question Set'!$G$260:$G$263,"In Progress"),IF(_xlpm.ip=0,"-",_xlpm.ip)) -> 2 | J53: =_xlfn.LET(_xlpm.y,COUNTIF('Question Set'!$G$260:$G$263,"Yes"),IF(_xlpm.y=0,"-",_xlpm.y)) -> 2 | K53: =N(H53)+(N(I53)*2)+(N(J53)*3) -> 10 | L53: of | M53: =(SUM(F53:J53)*3) -> 12
C54: Environmental Monitoring & Facility Protections | D54: 3 | E54: =_xlfn.LET(_xlpm.na,COUNTIF('Question Set'!$G$266:$G$268,"Not Applicable"),IF(_xlpm.na=0,"-",_xlpm.na)) -> 1 | F54: =_xlfn.LET(_xlpm.u,COUNTIF('Question Set'!$G$266:$G$268,"Unknown"),IF(_xlpm.u=0,"-",_xlpm.u)) -> - | G54: =_xlfn.LET(_xlpm.n,COUNTIF('Question Set'!$G$266:$G$268,"No"),IF(_xlpm.n=0,"-",_xlpm.n)) -> 1 | H54: =_xlfn.LET(_xlpm.pl,COUNTIF('Question Set'!$G$266:$G$268,"Planned"),IF(_xlpm.pl=0,"-",_xlpm.pl)) -> - | I54: =_xlfn.LET(_xlpm.ip,COUNTIF('Question Set'!$G$266:$G$268,"In Progress"),IF(_xlpm.ip=0,"-",_xlpm.ip)) -> - | J54: =_xlfn.LET(_xlpm.y,COUNTIF('Question Set'!$G$266:$G$268,"Yes"),IF(_xlpm.y=0,"-",_xlpm.y)) -> 1 | K54: =N(H54)+(N(I54)*2)+(N(J54)*3) -> 3 | L54: of | M54: =(SUM(F54:J54)*3) -> 6
C55: Domain Total | D55: =SUM(D50:D54) -> 18 | E55: =_xlfn.LET(_xlpm.x,SUM(E50:E54),IF(_xlpm.x=0,"-",_xlpm.x)) -> 1 | F55: =_xlfn.LET(_xlpm.x,SUM(F50:F54),IF(_xlpm.x=0,"-",_xlpm.x)) -> - | G55: =_xlfn.LET(_xlpm.x,SUM(G50:G54),IF(_xlpm.x=0,"-",_xlpm.x)) -> 7 | H55: =_xlfn.LET(_xlpm.x,SUM(H50:H54),IF(_xlpm.x=0,"-",_xlpm.x)) -> - | I55: =_xlfn.LET(_xlpm.x,SUM(I50:I54),IF(_xlpm.x=0,"-",_xlpm.x)) -> 4 | J55: =_xlfn.LET(_xlpm.x,SUM(J50:J54),IF(_xlpm.x=0,"-",_xlpm.x)) -> 6 | K55: =N(H55)+(N(I55)*2)+(N(J55)*3) -> 26 | L55: of | M55: =(SUM(F55:J55)*3) -> 51
B56: Third-Party Security & Supply Chain Management | C56: Third-Party & Hosted Service Security | D56: 2 | E56: =_xlfn.LET(_xlpm.na,COUNTIF('Question Set'!$G$272:$G$273,"Not Applicable"),IF(_xlpm.na=0,"-",_xlpm.na)) -> - | F56: =_xlfn.LET(_xlpm.u,COUNTIF('Question Set'!$G$272:$G$273,"Unknown"),IF(_xlpm.u=0,"-",_xlpm.u)) -> - | G56: =_xlfn.LET(_xlpm.n,COUNTIF('Question Set'!$G$272:$G$273,"No"),IF(_xlpm.n=0,"-",_xlpm.n)) -> 1 | H56: =_xlfn.LET(_xlpm.pl,COUNTIF('Question Set'!$G$272:$G$273,"Planned"),IF(_xlpm.pl=0,"-",_xlpm.pl)) -> 1 | I56: =_xlfn.LET(_xlpm.ip,COUNTIF('Question Set'!$G$272:$G$273,"In Progress"),IF(_xlpm.ip=0,"-",_xlpm.ip)) -> - | J56: =_xlfn.LET(_xlpm.y,COUNTIF('Question Set'!$G$272:$G$273,"Yes"),IF(_xlpm.y=0,"-",_xlpm.y)) -> - | K56: =N(H56)+(N(I56)*2)+(N(J56)*3) -> 1 | L56: of | M56: =(SUM(F56:J56)*3) -> 6
C57: Third-Party Asset Inventory | D57: 1 | E57: =_xlfn.LET(_xlpm.na,COUNTIF('Question Set'!$G$276,"Not Applicable"),IF(_xlpm.na=0,"-",_xlpm.na)) -> - | F57: =_xlfn.LET(_xlpm.u,COUNTIF('Question Set'!$G$276,"Unknown"),IF(_xlpm.u=0,"-",_xlpm.u)) -> - | G57: =_xlfn.LET(_xlpm.n,COUNTIF('Question Set'!$G$276,"No"),IF(_xlpm.n=0,"-",_xlpm.n)) -> - | H57: =_xlfn.LET(_xlpm.pl,COUNTIF('Question Set'!$G$276,"Planned"),IF(_xlpm.pl=0,"-",_xlpm.pl)) -> 1 | I57: =_xlfn.LET(_xlpm.ip,COUNTIF('Question Set'!$G$276,"In Progress"),IF(_xlpm.ip=0,"-",_xlpm.ip)) -> - | J57: =_xlfn.LET(_xlpm.y,COUNTIF('Question Set'!$G$276,"Yes"),IF(_xlpm.y=0,"-",_xlpm.y)) -> - | K57: =N(H57)+(N(I57)*2)+(N(J57)*3) -> 1 | L57: of | M57: =(SUM(F57:J57)*3) -> 3
C58: Personnel Screening & Vetting | D58: 1 | E58: =_xlfn.LET(_xlpm.na,COUNTIF('Question Set'!$G$279,"Not Applicable"),IF(_xlpm.na=0,"-",_xlpm.na)) -> - | F58: =_xlfn.LET(_xlpm.u,COUNTIF('Question Set'!$G$279,"Unknown"),IF(_xlpm.u=0,"-",_xlpm.u)) -> - | G58: =_xlfn.LET(_xlpm.n,COUNTIF('Question Set'!$G$279,"No"),IF(_xlpm.n=0,"-",_xlpm.n)) -> 1 | H58: =_xlfn.LET(_xlpm.pl,COUNTIF('Question Set'!$G$279,"Planned"),IF(_xlpm.pl=0,"-",_xlpm.pl)) -> - | I58: =_xlfn.LET(_xlpm.ip,COUNTIF('Question Set'!$G$279,"In Progress"),IF(_xlpm.ip=0,"-",_xlpm.ip)) -> - | J58: =_xlfn.LET(_xlpm.y,COUNTIF('Question Set'!$G$279,"Yes"),IF(_xlpm.y=0,"-",_xlpm.y)) -> - | K58: =N(H58)+(N(I58)*2)+(N(J58)*3) -> 0 | L58: of | M58: =(SUM(F58:J58)*3) -> 3
C59: Procurement, Delivery & Supply Validation | D59: 3 | E59: =_xlfn.LET(_xlpm.na,COUNTIF('Question Set'!$G$282:$G$284,"Not Applicable"),IF(_xlpm.na=0,"-",_xlpm.na)) -> - | F59: =_xlfn.LET(_xlpm.u,COUNTIF('Question Set'!$G$282:$G$284,"Unknown"),IF(_xlpm.u=0,"-",_xlpm.u)) -> - | G59: =_xlfn.LET(_xlpm.n,COUNTIF('Question Set'!$G$282:$G$284,"No"),IF(_xlpm.n=0,"-",_xlpm.n)) -> 2 | H59: =_xlfn.LET(_xlpm.pl,COUNTIF('Question Set'!$G$282:$G$284,"Planned"),IF(_xlpm.pl=0,"-",_xlpm.pl)) -> 1 | I59: =_xlfn.LET(_xlpm.ip,COUNTIF('Question Set'!$G$282:$G$284,"In Progress"),IF(_xlpm.ip=0,"-",_xlpm.ip)) -> - | J59: =_xlfn.LET(_xlpm.y,COUNTIF('Question Set'!$G$282:$G$284,"Yes"),IF(_xlpm.y=0,"-",_xlpm.y)) -> - | K59: =N(H59)+(N(I59)*2)+(N(J59)*3) -> 1 | L59: of | M59: =(SUM(F59:J59)*3) -> 9
C60: Domain Total | D60: =SUM(D56:D59) -> 7 | E60: =_xlfn.LET(_xlpm.x,SUM(E56:E59),IF(_xlpm.x=0,"-",_xlpm.x)) -> - | F60: =_xlfn.LET(_xlpm.x,SUM(F56:F59),IF(_xlpm.x=0,"-",_xlpm.x)) -> - | G60: =_xlfn.LET(_xlpm.x,SUM(G56:G59),IF(_xlpm.x=0,"-",_xlpm.x)) -> 4 | H60: =_xlfn.LET(_xlpm.x,SUM(H56:H59),IF(_xlpm.x=0,"-",_xlpm.x)) -> 3 | I60: =_xlfn.LET(_xlpm.x,SUM(I56:I59),IF(_xlpm.x=0,"-",_xlpm.x)) -> - | J60: =_xlfn.LET(_xlpm.x,SUM(J56:J59),IF(_xlpm.x=0,"-",_xlpm.x)) -> - | K60: =N(H60)+(N(I60)*2)+(N(J60)*3) -> 3 | L60: of | M60: =(SUM(F60:J60)*3) -> 21
B61: Assessment, Testing & Remediation Management | C61: Security Assessment & Vulnerability Management | D61: 4 | E61: =_xlfn.LET(_xlpm.na,COUNTIF('Question Set'!$G$288:$G$291,"Not Applicable"),IF(_xlpm.na=0,"-",_xlpm.na)) -> - | F61: =_xlfn.LET(_xlpm.u,COUNTIF('Question Set'!$G$288:$G$291,"Unknown"),IF(_xlpm.u=0,"-",_xlpm.u)) -> - | G61: =_xlfn.LET(_xlpm.n,COUNTIF('Question Set'!$G$288:$G$291,"No"),IF(_xlpm.n=0,"-",_xlpm.n)) -> 3 | H61: =_xlfn.LET(_xlpm.pl,COUNTIF('Question Set'!$G$288:$G$291,"Planned"),IF(_xlpm.pl=0,"-",_xlpm.pl)) -> - | I61: =_xlfn.LET(_xlpm.ip,COUNTIF('Question Set'!$G$288:$G$291,"In Progress"),IF(_xlpm.ip=0,"-",_xlpm.ip)) -> - | J61: =_xlfn.LET(_xlpm.y,COUNTIF('Question Set'!$G$288:$G$291,"Yes"),IF(_xlpm.y=0,"-",_xlpm.y)) -> 1 | K61: =N(H61)+(N(I61)*2)+(N(J61)*3) -> 3 | L61: of | M61: =(SUM(F61:J61)*3) -> 12
C62: Issue Tracking & Risk Response | D62: 2 | E62: =_xlfn.LET(_xlpm.na,COUNTIF('Question Set'!$G$294:$G$295,"Not Applicable"),IF(_xlpm.na=0,"-",_xlpm.na)) -> - | F62: =_xlfn.LET(_xlpm.u,COUNTIF('Question Set'!$G$294:$G$295,"Unknown"),IF(_xlpm.u=0,"-",_xlpm.u)) -> 1 | G62: =_xlfn.LET(_xlpm.n,COUNTIF('Question Set'!$G$294:$G$295,"No"),IF(_xlpm.n=0,"-",_xlpm.n)) -> 1 | H62: =_xlfn.LET(_xlpm.pl,COUNTIF('Question Set'!$G$294:$G$295,"Planned"),IF(_xlpm.pl=0,"-",_xlpm.pl)) -> - | I62: =_xlfn.LET(_xlpm.ip,COUNTIF('Question Set'!$G$294:$G$295,"In Progress"),IF(_xlpm.ip=0,"-",_xlpm.ip)) -> - | J62: =_xlfn.LET(_xlpm.y,COUNTIF('Question Set'!$G$294:$G$295,"Yes"),IF(_xlpm.y=0,"-",_xlpm.y)) -> - | K62: =N(H62)+(N(I62)*2)+(N(J62)*3) -> 0 | L62: of | M62: =(SUM(F62:J62)*3) -> 6
C63: Domain Total | D63: =SUM(D61:D62) -> 6 | E63: =_xlfn.LET(_xlpm.x,SUM(E61:E62),IF(_xlpm.x=0,"-",_xlpm.x)) -> - | F63: =_xlfn.LET(_xlpm.x,SUM(F61:F62),IF(_xlpm.x=0,"-",_xlpm.x)) -> 1 | G63: =_xlfn.LET(_xlpm.x,SUM(G61:G62),IF(_xlpm.x=0,"-",_xlpm.x)) -> 4 | H63: =_xlfn.LET(_xlpm.x,SUM(H61:H62),IF(_xlpm.x=0,"-",_xlpm.x)) -> - | I63: =_xlfn.LET(_xlpm.x,SUM(I61:I62),IF(_xlpm.x=0,"-",_xlpm.x)) -> - | J63: =_xlfn.LET(_xlpm.x,SUM(J61:J62),IF(_xlpm.x=0,"-",_xlpm.x)) -> 1 | K63: =N(H63)+(N(I63)*2)+(N(J63)*3) -> 3 | L63: of | M63: =(SUM(F63:J63)*3) -> 18
B64: Training, Awareness & Behavioral Governance | C64: Cybersecurity Training & Compliance | D64: 5 | E64: =_xlfn.LET(_xlpm.na,COUNTIF('Question Set'!$G$299:$G$303,"Not Applicable"),IF(_xlpm.na=0,"-",_xlpm.na)) -> 1 | F64: =_xlfn.LET(_xlpm.u,COUNTIF('Question Set'!$G$299:$G$303,"Unknown"),IF(_xlpm.u=0,"-",_xlpm.u)) -> - | G64: =_xlfn.LET(_xlpm.n,COUNTIF('Question Set'!$G$299:$G$303,"No"),IF(_xlpm.n=0,"-",_xlpm.n)) -> - | H64: =_xlfn.LET(_xlpm.pl,COUNTIF('Question Set'!$G$299:$G$303,"Planned"),IF(_xlpm.pl=0,"-",_xlpm.pl)) -> - | I64: =_xlfn.LET(_xlpm.ip,COUNTIF('Question Set'!$G$299:$G$303,"In Progress"),IF(_xlpm.ip=0,"-",_xlpm.ip)) -> - | J64: =_xlfn.LET(_xlpm.y,COUNTIF('Question Set'!$G$299:$G$303,"Yes"),IF(_xlpm.y=0,"-",_xlpm.y)) -> 4 | K64: =N(H64)+(N(I64)*2)+(N(J64)*3) -> 12 | L64: of | M64: =(SUM(F64:J64)*3) -> 12
C65: Role-Specific Training & Handling Responsibilities | D65: 3 | E65: =_xlfn.LET(_xlpm.na,COUNTIF('Question Set'!$G$306:$G$308,"Not Applicable"),IF(_xlpm.na=0,"-",_xlpm.na)) -> - | F65: =_xlfn.LET(_xlpm.u,COUNTIF('Question Set'!$G$306:$G$308,"Unknown"),IF(_xlpm.u=0,"-",_xlpm.u)) -> - | G65: =_xlfn.LET(_xlpm.n,COUNTIF('Question Set'!$G$306:$G$308,"No"),IF(_xlpm.n=0,"-",_xlpm.n)) -> 1 | H65: =_xlfn.LET(_xlpm.pl,COUNTIF('Question Set'!$G$306:$G$308,"Planned"),IF(_xlpm.pl=0,"-",_xlpm.pl)) -> 1 | I65: =_xlfn.LET(_xlpm.ip,COUNTIF('Question Set'!$G$306:$G$308,"In Progress"),IF(_xlpm.ip=0,"-",_xlpm.ip)) -> - | J65: =_xlfn.LET(_xlpm.y,COUNTIF('Question Set'!$G$306:$G$308,"Yes"),IF(_xlpm.y=0,"-",_xlpm.y)) -> 1 | K65: =N(H65)+(N(I65)*2)+(N(J65)*3) -> 4 | L65: of | M65: =(SUM(F65:J65)*3) -> 9
C66: User Conduct Policies & Acknowledgements | D66: 3 | E66: =_xlfn.LET(_xlpm.na,COUNTIF('Question Set'!$G$311:$G$313,"Not Applicable"),IF(_xlpm.na=0,"-",_xlpm.na)) -> - | F66: =_xlfn.LET(_xlpm.u,COUNTIF('Question Set'!$G$311:$G$313,"Unknown"),IF(_xlpm.u=0,"-",_xlpm.u)) -> - | G66: =_xlfn.LET(_xlpm.n,COUNTIF('Question Set'!$G$311:$G$313,"No"),IF(_xlpm.n=0,"-",_xlpm.n)) -> 2 | H66: =_xlfn.LET(_xlpm.pl,COUNTIF('Question Set'!$G$311:$G$313,"Planned"),IF(_xlpm.pl=0,"-",_xlpm.pl)) -> - | I66: =_xlfn.LET(_xlpm.ip,COUNTIF('Question Set'!$G$311:$G$313,"In Progress"),IF(_xlpm.ip=0,"-",_xlpm.ip)) -> 1 | J66: =_xlfn.LET(_xlpm.y,COUNTIF('Question Set'!$G$311:$G$313,"Yes"),IF(_xlpm.y=0,"-",_xlpm.y)) -> - | K66: =N(H66)+(N(I66)*2)+(N(J66)*3) -> 2 | L66: of | M66: =(SUM(F66:J66)*3) -> 9
C67: Domain Total | D67: =SUM(D64:D66) -> 11 | E67: =_xlfn.LET(_xlpm.x,SUM(E64:E66),IF(_xlpm.x=0,"-",_xlpm.x)) -> 1 | F67: =_xlfn.LET(_xlpm.x,SUM(F64:F66),IF(_xlpm.x=0,"-",_xlpm.x)) -> - | G67: =_xlfn.LET(_xlpm.x,SUM(G64:G66),IF(_xlpm.x=0,"-",_xlpm.x)) -> 3 | H67: =_xlfn.LET(_xlpm.x,SUM(H64:H66),IF(_xlpm.x=0,"-",_xlpm.x)) -> 1 | I67: =_xlfn.LET(_xlpm.x,SUM(I64:I66),IF(_xlpm.x=0,"-",_xlpm.x)) -> 1 | J67: =_xlfn.LET(_xlpm.x,SUM(J64:J66),IF(_xlpm.x=0,"-",_xlpm.x)) -> 5 | K67: =N(H67)+(N(I67)*2)+(N(J67)*3) -> 18 | L67: of | M67: =(SUM(F67:J67)*3) -> 30

Sheet Domain-Level Score Table
B2: Domain | C2: Not Applicable | D2: Unknown | E2: No | F2: Planned | G2: In Progress | H2: Yes | I2: Points | J2: of possible | K2: TOTAL
B3: Governance, Risk & Strategy | C3: ='Full Score Table'!E8 -> - | D3: ='Full Score Table'!F8 -> - | E3: ='Full Score Table'!G8 -> 7 | F3: ='Full Score Table'!H8 -> 1 | G3: ='Full Score Table'!I8 -> 2 | H3: ='Full Score Table'!J8 -> 6 | I3: ='Full Score Table'!K8 -> 23 | J3: of | K3: ='Full Score Table'!M8 -> 48
B4: Identity, Authentication & Access Management | C4: ='Full Score Table'!E15 -> - | D4: ='Full Score Table'!F15 -> 1 | E4: ='Full Score Table'!G15 -> 9 | F4: ='Full Score Table'!H15 -> - | G4: ='Full Score Table'!I15 -> 13 | H4: ='Full Score Table'!J15 -> 7 | I4: ='Full Score Table'!K15 -> 47 | J4: of | K4: ='Full Score Table'!M15 -> 90
B5: Data Security & Lifecycle Management | C5: ='Full Score Table'!E19 -> - | D5: ='Full Score Table'!F19 -> - | E5: ='Full Score Table'!G19 -> 3 | F5: ='Full Score Table'!H19 -> 2 | G5: ='Full Score Table'!I19 -> 5 | H5: ='Full Score Table'!J19 -> 2 | I5: ='Full Score Table'!K19 -> 18 | J5: of | K5: ='Full Score Table'!M19 -> 36
B6: Network & Communications Governance | C6: ='Full Score Table'!E26 -> 2 | D6: ='Full Score Table'!F26 -> 3 | E6: ='Full Score Table'!G26 -> 8 | F6: ='Full Score Table'!H26 -> 3 | G6: ='Full Score Table'!I26 -> 9 | H6: ='Full Score Table'!J26 -> 4 | I6: ='Full Score Table'!K26 -> 33 | J6: of | K6: ='Full Score Table'!M26 -> 81
B7: Endpoint Security & Configuration Management | C7: ='Full Score Table'!E31 -> 3 | D7: ='Full Score Table'!F31 -> - | E7: ='Full Score Table'!G31 -> 8 | F7: ='Full Score Table'!H31 -> 1 | G7: ='Full Score Table'!I31 -> 1 | H7: ='Full Score Table'!J31 -> 6 | I7: ='Full Score Table'!K31 -> 21 | J7: of | K7: ='Full Score Table'!M31 -> 48
B8: Cryptography, Encryption & Key Management Governance | C8: ='Full Score Table'!E35 -> 1 | D8: ='Full Score Table'!F35 -> 1 | E8: ='Full Score Table'!G35 -> 8 | F8: ='Full Score Table'!H35 -> - | G8: ='Full Score Table'!I35 -> - | H8: ='Full Score Table'!J35 -> - | I8: ='Full Score Table'!K35 -> 0 | J8: of | K8: ='Full Score Table'!M35 -> 27
B9: Logging, Monitoring & Event Detection | C9: ='Full Score Table'!E40 -> - | D9: ='Full Score Table'!F40 -> - | E9: ='Full Score Table'!G40 -> 9 | F9: ='Full Score Table'!H40 -> - | G9: ='Full Score Table'!I40 -> 6 | H9: ='Full Score Table'!J40 -> - | I9: ='Full Score Table'!K40 -> 12 | J9: of | K9: ='Full Score Table'!M40 -> 45
B10: Response, Recovery & Forensic Readiness | C10: ='Full Score Table'!E44 -> - | D10: ='Full Score Table'!F44 -> - | E10: ='Full Score Table'!G44 -> 2 | F10: ='Full Score Table'!H44 -> 2 | G10: ='Full Score Table'!I44 -> 4 | H10: ='Full Score Table'!J44 -> 2 | I10: ='Full Score Table'!K44 -> 16 | J10: of | K10: ='Full Score Table'!M44 -> 30
B11: Business Continuity & Environmental Resilience | C11: ='Full Score Table'!E49 -> 1 | D11: ='Full Score Table'!F49 -> 1 | E11: ='Full Score Table'!G49 -> - | F11: ='Full Score Table'!H49 -> 2 | G11: ='Full Score Table'!I49 -> 10 | H11: ='Full Score Table'!J49 -> 1 | I11: ='Full Score Table'!K49 -> 25 | J11: of | K11: ='Full Score Table'!M49 -> 42
B12: Physical & Environmental Security Management | C12: ='Full Score Table'!E55 -> 1 | D12: ='Full Score Table'!F55 -> - | E12: ='Full Score Table'!G55 -> 7 | F12: ='Full Score Table'!H55 -> - | G12: ='Full Score Table'!I55 -> 4 | H12: ='Full Score Table'!J55 -> 6 | I12: ='Full Score Table'!K55 -> 26 | J12: of | K12: ='Full Score Table'!M55 -> 51
B13: Third-Party Security & Supply Chain Management | C13: ='Full Score Table'!E60 -> - | D13: ='Full Score Table'!F60 -> - | E13: ='Full Score Table'!G60 -> 4 | F13: ='Full Score Table'!H60 -> 3 | G13: ='Full Score Table'!I60 -> - | H13: ='Full Score Table'!J60 -> - | I13: ='Full Score Table'!K60 -> 3 | J13: of | K13: ='Full Score Table'!M60 -> 21
B14: Assessment, Testing & Remediation Management | C14: ='Full Score Table'!E63 -> - | D14: ='Full Score Table'!F63 -> 1 | E14: ='Full Score Table'!G63 -> 4 | F14: ='Full Score Table'!H63 -> - | G14: ='Full Score Table'!I63 -> - | H14: ='Full Score Table'!J63 -> 1 | I14: ='Full Score Table'!K63 -> 3 | J14: of | K14: ='Full Score Table'!M63 -> 18
B15: Training, Awareness & Behavioral Governance | C15: ='Full Score Table'!E67 -> 1 | D15: ='Full Score Table'!F67 -> - | E15: ='Full Score Table'!G67 -> 3 | F15: ='Full Score Table'!H67 -> 1 | G15: ='Full Score Table'!I67 -> 1 | H15: ='Full Score Table'!J67 -> 5 | I15: ='Full Score Table'!K67 -> 18 | J15: of | K15: ='Full Score Table'!M67 -> 30
B16: OVERALL | C16: ='Full Score Table'!E3 -> 9 | D16: ='Full Score Table'!F3 -> 7 | E16: ='Full Score Table'!G3 -> 72 | F16: ='Full Score Table'!H3 -> 15 | G16: ='Full Score Table'!I3 -> 55 | H16: ='Full Score Table'!J3 -> 40 | I16: ='Full Score Table'!K3 -> 245 | J16: of | K16: ='Full Score Table'!M3 -> 567

Sheet -HIDE- Drop Downs | Maths
A1: - SELECT RATING - | N1: ('Question Set'!$G
L2: Ranges:
A3: YES | L3: 1. Governance, Risk & Strategy | N3: 2-25
A4: IN PROGRESS | M4: A. Executive Leadership & Resource Allocation | N4: 4-6
A5: PLANNED | M5: B. Policy & Asset Inventory Management | N5: 9-11
A6: NO | M6: C. Role Definition & Governance Oversight | N6: 14-18
A7: - | M7: D. Risk Assessment & Management Strategy | N7: 21-25
A8: UNKNOWN
A9: NOT APPLICABLE | L9: 2. Identity, Authentication & Access Management | N9: 27-68
M10: A. Access Control Governance & Management | N10: 29-34
M11: B. Account & Credential Lifecycle Management | N11: 37-41
M12: C. Authentication & Credential Governance | N12: 44-48
M13: D. Authorization & Least Privilege Enforcement | N13: 51-54
M14: E. Privileged Access Governance & Monitoring | N14: 57-61
A15: E-J | C15: Points | D15: Possible | E15: Percent | M15: F. Session Management & Monitoring | N15: 64-68
A16: 8 | B16: =_xlfn.CONCAT(F16, " (",G16, ")") -> Governance, Risk & Strategy (23 of 48) | C16: ='Domain-Level Score Table'!I3 -> 23 | D16: ='Domain-Level Score Table'!K3 -> 48 | E16: =C16/D16 -> 0.47916667 | F16: Governance, Risk & Strategy | G16: =_xlfn.CONCAT(C16, " of ", D16) -> 23 of 48
A17: 15 | B17: =_xlfn.CONCAT(F17, " (",G17, ")") -> Identity, Authentication & Access Management (47 of 90) | C17: ='Domain-Level Score Table'!I4 -> 47 | D17: ='Domain-Level Score Table'!K4 -> 90 | E17: =C17/D17 -> 0.52222222 | F17: Identity, Authentication & Access Management | G17: =_xlfn.CONCAT(C17, " of ", D17) -> 47 of 90 | L17: 3. Data Security & Lifecycle Management | N17: 70-87
A18: 19 | B18: =_xlfn.CONCAT(F18, " (",G18, ")") -> Data Security & Lifecycle Management (18 of 36) | C18: ='Domain-Level Score Table'!I5 -> 18 | D18: ='Domain-Level Score Table'!K5 -> 36 | E18: =C18/D18 -> 0.5 | F18: Data Security & Lifecycle Management | G18: =_xlfn.CONCAT(C18, " of ", D18) -> 18 of 36 | M18: A. Data Classification & Labelig | N18: 72-74
A19: 26 | B19: =_xlfn.CONCAT(F19, " (",G19, ")") -> Network & Communications Governance (33 of 81) | C19: ='Domain-Level Score Table'!I6 -> 33 | D19: ='Domain-Level Score Table'!K6 -> 81 | E19: =C19/D19 -> 0.40740741 | F19: Network & Communications Governance | G19: =_xlfn.CONCAT(C19, " of ", D19) -> 33 of 81 | M19: B. Data Protection & Lifecycle Management | N19: 77-82
A20: 31 | B20: =_xlfn.CONCAT(F20, " (",G20, ")") -> Endpoint Security & Configuration Management (21 of 48) | C20: ='Domain-Level Score Table'!I7 -> 21 | D20: ='Domain-Level Score Table'!K7 -> 48 | E20: =C20/D20 -> 0.4375 | F20: Endpoint Security & Configuration Management | G20: =_xlfn.CONCAT(C20, " of ", D20) -> 21 of 48 | M20: C. Data Access Monitoring & Disclosure Management | N20: 85-87
A21: 35 | B21: =_xlfn.CONCAT(F21, " (",G21, ")") -> Cryptography, Encryption & Key Management Governance (0 of 27) | C21: ='Domain-Level Score Table'!I8 -> 0 | D21: ='Domain-Level Score Table'!K8 -> 27 | E21: =C21/D21 -> 0 | F21: Cryptography, Encryption & Key Management Governance | G21: =_xlfn.CONCAT(C21, " of ", D21) -> 0 of 27
A22: 40 | B22: =_xlfn.CONCAT(F22, " (",G22, ")") -> Logging, Monitoring & Event Detection (12 of 45) | C22: ='Domain-Level Score Table'!I9 -> 12 | D22: ='Domain-Level Score Table'!K9 -> 45 | E22: =C22/D22 -> 0.26666667 | F22: Logging, Monitoring & Event Detection | G22: =_xlfn.CONCAT(C22, " of ", D22) -> 12 of 45 | L22: 4. Network & Communications Governance | N22: 89-129
A23: 44 | B23: =_xlfn.CONCAT(F23, " (",G23, ")") -> Response, Recovery & Forensic Readiness (16 of 30) | C23: ='Domain-Level Score Table'!I10 -> 16 | D23: ='Domain-Level Score Table'!K10 -> 30 | E23: =C23/D23 -> 0.53333333 | F23: Response, Recovery & Forensic Readiness | G23: =_xlfn.CONCAT(C23, " of ", D23) -> 16 of 30 | M23: A. Network Infrastructure & Boundary Controls | N23: 91-95
A24: 49 | B24: =_xlfn.CONCAT(F24, " (",G24, ")") -> Business Continuity & Environmental Resilience (25 of 42) | C24: ='Domain-Level Score Table'!I11 -> 25 | D24: ='Domain-Level Score Table'!K11 -> 42 | E24: =C24/D24 -> 0.5952381 | F24: Business Continuity & Environmental Resilience | G24: =_xlfn.CONCAT(C24, " of ", D24) -> 25 of 42 | M24: B. Network Traffic & Threat Controls | N24: 98-102
A25: 55 | B25: =_xlfn.CONCAT(F25, " (",G25, ")") -> Physical & Environmental Security Management (26 of 51) | C25: ='Domain-Level Score Table'!I12 -> 26 | D25: ='Domain-Level Score Table'!K12 -> 51 | E25: =C25/D25 -> 0.50980392 | F25: Physical & Environmental Security Management | G25: =_xlfn.CONCAT(C25, " of ", D25) -> 26 of 51 | M25: C. DNS Governance & Security Controls | N25: 105-110
A26: 60 | B26: =_xlfn.CONCAT(F26, " (",G26, ")") -> Third-Party Security & Supply Chain Management (3 of 21) | C26: ='Domain-Level Score Table'!I13 -> 3 | D26: ='Domain-Level Score Table'!K13 -> 21 | E26: =C26/D26 -> 0.14285714 | F26: Third-Party Security & Supply Chain Management | G26: =_xlfn.CONCAT(C26, " of ", D26) -> 3 of 21 | M26: D. Email System Security & Threat Protection | N26: 113-116
A27: 63 | B27: =_xlfn.CONCAT(F27, " (",G27, ")") -> Assessment, Testing & Remediation Management (3 of 18) | C27: ='Domain-Level Score Table'!I14 -> 3 | D27: ='Domain-Level Score Table'!K14 -> 18 | E27: =C27/D27 -> 0.16666667 | F27: Assessment, Testing & Remediation Management | G27: =_xlfn.CONCAT(C27, " of ", D27) -> 3 of 18 | M27: E. Wireless & Cellular Communications Security | N27: 119-123
A28: 67 | B28: =_xlfn.CONCAT(F28, " (",G28, ")") -> Training, Awareness & Behavioral Governance (18 of 30) | C28: ='Domain-Level Score Table'!I15 -> 18 | D28: ='Domain-Level Score Table'!K15 -> 30 | E28: =C28/D28 -> 0.6 | F28: Training, Awareness & Behavioral Governance | G28: =_xlfn.CONCAT(C28, " of ", D28) -> 18 of 30 | M28: F. Device & Remote Connectivity Controls | N28: 126-129
L30: 5. Endpoint Security & Configuration Management | N30: 131-157
M31: A. Baseline Configuration & Asset Management | N31: 133-137
B32: =B16 -> Governance, Risk & Strategy (23 of 48) | C32: =E16 -> 0.47916667 | D32: ='PSAP Information'!$B$13 -> 0.5 | M32: B. Service & Endpoint Hardening Controls | N32: 140-144
B33: =B17 -> Identity, Authentication & Access Management (47 of 90) | C33: =E17 -> 0.52222222 | D33: ='PSAP Information'!$B$13 -> 0.5 | M33: C. Configuration Change & Patch Management | N33: 147-151
B34: =B18 -> Data Security & Lifecycle Management (18 of 36) | C34: =E18 -> 0.5 | D34: ='PSAP Information'!$B$13 -> 0.5 | M34: D. Endpoint & Remote Device Security | N34: 154-157
B35: =B19 -> Network & Communications Governance (33 of 81) | C35: =E19 -> 0.40740741 | D35: ='PSAP Information'!$B$13 -> 0.5
B36: =B20 -> Endpoint Security & Configuration Management (21 of 48) | C36: =E20 -> 0.4375 | D36: ='PSAP Information'!$B$13 -> 0.5 | L36: 6. Cryptography, Encryption & Key Management Governance | N36: 159-174
B37: =B21 -> Cryptography, Encryption & Key Management Governance (0 of 27) | C37: =E21 -> 0 | D37: ='PSAP Information'!$B$13 -> 0.5 | M37: A. Encryption & Cryptography Governance | N37: 161-163
B38: =B22 -> Logging, Monitoring & Event Detection (12 of 45) | C38: =E22 -> 0.26666667 | D38: ='PSAP Information'!$B$13 -> 0.5 | M38: B. PKI & Certificate Management | N38: 166-168
B39: =B23 -> Response, Recovery & Forensic Readiness (16 of 30) | C39: =E23 -> 0.53333333 | D39: ='PSAP Information'!$B$13 -> 0.5 | M39: C. Cryptographic Key Governance & Availability | N39: 171-174
B40: =B24 -> Business Continuity & Environmental Resilience (25 of 42) | C40: =E24 -> 0.5952381 | D40: ='PSAP Information'!$B$13 -> 0.5
B41: =B25 -> Physical & Environmental Security Management (26 of 51) | C41: =E25 -> 0.50980392 | D41: ='PSAP Information'!$B$13 -> 0.5 | L41: 7. Logging, Monitoring & Event Detection | N41: 176-198
B42: =B26 -> Third-Party Security & Supply Chain Management (3 of 21) | C42: =E26 -> 0.14285714 | D42: ='PSAP Information'!$B$13 -> 0.5 | M42: A. Logging Policy, Content & Review | N42: 178-181
B43: =B27 -> Assessment, Testing & Remediation Management (3 of 18) | C43: =E27 -> 0.16666667 | D43: ='PSAP Information'!$B$13 -> 0.5 | M43: B. Continuous Monitoring & Threat Detection | N43: 184-188
B44: =B28 -> Training, Awareness & Behavioral Governance (18 of 30) | C44: =E28 -> 0.6 | D44: ='PSAP Information'!$B$13 -> 0.5 | M44: C. Security Event Review & Detection | N44: 191-194
M45: D. Time Synchronization & Log Integrity | N45: 197-198
L47: 8. Response, Recovery, & Forensic Readiness | N47: 200-215
M48: A. Incident Reponse Planning & Procedures | N48: 202-203
M49: B. Incident Response Execution & Resilience | N49: 206-209
M50: C. Forensic Readiness & Evidence Management | N50: 212-215
L52: 9. Business Continuity & Environmental Resilience | N52: 217-239
M53: A. Cotinuity Planning & Recovery | N53: 219-222
M54: B. Backup & Restoration Management | N54: 225-228
M55: C. Redundancy, Recovery & Resilience | N55: 231-234
M56: D. Power & Environmental Resilience | N56: 237-239
L58: 10. Physical & Environmental Security | N58: 241-268
M59: A. Facility Access Control & Perimeter Security | N59: 243-248
M60: B. Visitor Management | N60: 251-252
M61: C. Physical Access Monitoring & Logging | N61: 255-257
M62: D. Secure Placement & Physical Safeguards | N62: 260-263
M63: E. Environmental Monitoring & Facility Protections | N63: 266-268
L65: 11. Third-Party Security & Supply Chain Management | N65: 270-284
M66: A. Third-Party & Hosted Service Security | N66: 272-273
M67: B. Third-Party Asset Inventory | N67: 276
M68: C. Personnel Screening & Vetting | N68: 279
M69: D. Procurement, Delivery & Supply Validation | N69: 282-284
L71: 12. Assessment, Testing, & Remediation Management | N71: 286-295
M72: A. Security Assessment & Vulnerability Management | N72: 288-291
M73: B. Issue Tracking & Risk Response | N73: 294-295
L75: 13. Training, Awareness & Behavioral Governance | N75: 297-313
M76: A. Cybersecurity Training & Competency | N76: 299-303
M77: B. Role-Specific Training & Handling Responsibilities | N77: 306-308
M78: C. User Conduct Policies & Acknowledgements | N78: 311-313
